Workbook

Sheet Budget
A1: Object | B1: Total of years | G1: Previous years | L1: 2024 | Q1: 2025 | V1: 2026 | AA1: 2027 and Following | AF1: Overall values | AK1: ProjectName | AL1: ProjectID | AM1: =B1 -> Total of years | AN1: Plan Values across years
B2: Budget | C2: Actual | D2: Commitment | E2: Assigned | F2: Available | G2: Budget | H2: Actual | I2: Commitment | J2: Assigned | K2: Available | L2: Budget | M2: Actual | N2: Commitment | O2: Assigned | P2: Available | Q2: Budget | R2: Actual | S2: Commitment | T2: Assigned | U2: Available | V2: Budget | W2: Actual | X2: Commitment | Y2: Assigned | Z2: Available | AA2: Budget | AB2: Actual | AC2: Commitment | AD2: Assigned | AE2: Available | AF2: Budget | AG2: Actual | AH2: Commitment | AI2: Assigned | AJ2: Available | AN2: =G1 -> Previous years | AO2: =L1 -> 2024 | AP2: =Q1 -> 2025 | AQ2: =V1 -> 2026 | AR2: =AA1 -> 2027 and Following | AS2: =AF1 -> Overall values
A3: 6* 600 MW Solar @ GSECL PRJ NG-C-SOL-001 | B3: 0 | C3: 0 | D3: 0 | E3: 0 | F3: 0 | G3: 0 | H3: 0 | I3: 0 | J3: 0 | K3: 0 | L3: 0 | M3: 0 | N3: 0 | O3: 0 | P3: 0 | Q3: 0 | R3: 0 | S3: 0 | T3: 0 | U3: 0 | V3: 0 | W3: 0 | X3: 0 | Y3: 0 | Z3: 0 | AA3: 0 | AB3: 0 | AC3: 0 | AD3: 0 | AE3: 0 | AF3: 0 | AG3: 0 | AH3: 0 | AI3: 0 | AJ3: 0 | AK3: 600 MW Solar @ GSECL | AL3: NG-C-SOL-001 | AM3: =VLOOKUP(AL3,Table1[],2,FALSE) -> #N/A | AN3: =VLOOKUP($AL3,Table1[],3,FALSE) -> #N/A | AO3: =VLOOKUP($AL3,Table1[],4,FALSE) -> #N/A | AP3: =VLOOKUP($AL3,Table1[],5,FALSE) -> #N/A | AQ3: =VLOOKUP($AL3,Table1[],6,FALSE) -> #N/A | AR3: =VLOOKUP($AL3,Table1[],7,FALSE) -> #N/A | AS3: =VLOOKUP($AL3,Table1[],8,FALSE) -> #N/A
A4: 6* 300 MW Solar Power P PRJ NL-C-BSP-001 | B4: 1.9137258e+10 | C4: 4.6622641e+09 | D4: 1.2756415e+09 | E4: 5.9379056e+09 | F4: 1.3199352e+10 | G4: 1.9527548e+09 | H4: 1.9527548e+09 | I4: 0 | J4: 1.9527548e+09 | K4: 0 | L4: 1.7184503e+10 | M4: 2.7095093e+09 | N4: 1.2756415e+09 | O4: 3.9851508e+09 | P4: 1.3199352e+10 | Q4: 0 | R4: 0 | S4: 0 | T4: 0 | U4: 0 | V4: 0 | W4: 0 | X4: 0 | Y4: 0 | Z4: 0 | AA4: 0 | AB4: 0 | AC4: 0 | AD4: 0 | AE4: 0 | AF4: 1.9137258e+10 | AG4: 4.6622641e+09 | AH4: 1.2756415e+09 | AI4: 5.9379056e+09 | AJ4: 1.3199352e+10 | AK4: 300 MW Solar Power P | AL4: NL-C-BSP-001 | AM4: =VLOOKUP(AL4,Table1[],2,FALSE) -> 17555000001 | AN4: =VLOOKUP(AL4,Table1[],3,FALSE) -> 17555000001 | AO4: =VLOOKUP($AL4,Table1[],4,FALSE) -> 0 | AP4: =VLOOKUP($AL4,Table1[],5,FALSE) -> 0 | AQ4: =VLOOKUP($AL4,Table1[],6,FALSE) -> 0 | AR4: =VLOOKUP($AL4,Table1[],7,FALSE) -> 0 | AS4: =VLOOKUP($AL4,Table1[],8,FALSE) -> 17575000001
A5: 6* CARD R&D Project PRJ NL-C-CRD-001 | B5: 0 | C5: 0 | D5: 0 | E5: 0 | F5: 0 | G5: 0 | H5: 0 | I5: 0 | J5: 0 | K5: 0 | L5: 0 | M5: 0 | N5: 0 | O5: 0 | P5: 0 | Q5: 0 | R5: 0 | S5: 0 | T5: 0 | U5: 0 | V5: 0 | W5: 0 | X5: 0 | Y5: 0 | Z5: 0 | AA5: 0 | AB5: 0 | AC5: 0 | AD5: 0 | AE5: 0 | AF5: 0 | AG5: 0 | AH5: 0 | AI5: 0 | AJ5: 0 | AK5: CARD R&D Project | AL5: NL-C-CRD-001 | AM5: =VLOOKUP(AL5,Table1[],2,FALSE) -> #N/A | AN5: =VLOOKUP(AL5,Table1[],3,FALSE) -> #N/A | AO5: =VLOOKUP($AL5,Table1[],4,FALSE) -> #N/A | AP5: =VLOOKUP($AL5,Table1[],5,FALSE) -> #N/A | AQ5: =VLOOKUP($AL5,Table1[],6,FALSE) -> #N/A | AR5: =VLOOKUP($AL5,Table1[],7,FALSE) -> #N/A | AS5: =VLOOKUP($AL5,Table1[],8,FALSE) -> #N/A
A6: 6* Lignite to disel cap PRJ NL-C-CRD-002 | B6: 3987309 | C6: 3987309 | D6: 0 | E6: 3987309 | F6: 0 | G6: 3987309 | H6: 3987309 | I6: 0 | J6: 3987309 | K6: 0 | L6: 0 | M6: 0 | N6: 0 | O6: 0 | P6: 0 | Q6: 0 | R6: 0 | S6: 0 | T6: 0 | U6: 0 | V6: 0 | W6: 0 | X6: 0 | Y6: 0 | Z6: 0 | AA6: 0 | AB6: 0 | AC6: 0 | AD6: 0 | AE6: 0 | AF6: 3987309 | AG6: 3987309 | AH6: 0 | AI6: 3987309 | AJ6: 0 | AK6: Lignite to disel cap | AL6: NL-C-CRD-002 | AM6: =VLOOKUP(AL6,Table1[],2,FALSE) -> 5945634 | AN6: =VLOOKUP(AL6,Table1[],3,FALSE) -> 5945634 | AO6: =VLOOKUP($AL6,Table1[],4,FALSE) -> 0 | AP6: =VLOOKUP($AL6,Table1[],5,FALSE) -> 0 | AQ6: =VLOOKUP($AL6,Table1[],6,FALSE) -> 0 | AR6: =VLOOKUP($AL6,Table1[],7,FALSE) -> 0 | AS6: =VLOOKUP($AL6,Table1[],8,FALSE) -> 5945634
A7: 6* CARD-IITM-Developmen PRJ NL-C-CRD-003 | B7: 13294999 | C7: 3679142.1 | D7: 9615856.8 | E7: 13294999 | F7: 0 | G7: 13294999 | H7: 3679142.1 | I7: 9615856.8 | J7: 13294999 | K7: 0 | L7: 0 | M7: 0 | N7: 0 | O7: 0 | P7: 0 | Q7: 0 | R7: 0 | S7: 0 | T7: 0 | U7: 0 | V7: 0 | W7: 0 | X7: 0 | Y7: 0 | Z7: 0 | AA7: 0 | AB7: 0 | AC7: 0 | AD7: 0 | AE7: 0 | AF7: 13294999 | AG7: 3679142.1 | AH7: 9615856.8 | AI7: 13294999 | AJ7: 0 | AK7: CARD-IITM-Developmen | AL7: NL-C-CRD-003 | AM7: =VLOOKUP(AL7,Table1[],2,FALSE) -> 18295400 | AN7: =VLOOKUP(AL7,Table1[],3,FALSE) -> 18295400 | AO7: =VLOOKUP($AL7,Table1[],4,FALSE) -> 0 | AP7: =VLOOKUP($AL7,Table1[],5,FALSE) -> 0 | AQ7: =VLOOKUP($AL7,Table1[],6,FALSE) -> 0 | AR7: =VLOOKUP($AL7,Table1[],7,FALSE) -> 0 | AS7: =VLOOKUP($AL7,Table1[],8,FALSE) -> 18295400
A8: 6* CAPEX PROJECT FOR CA PRJ NL-C-CRD-004 | B8: 8.0681444e+08 | C8: 3.6219046e+08 | D8: 2.4664061e+08 | E8: 6.0883108e+08 | F8: 1.9798336e+08 | G8: 2.4180404e+08 | H8: 2.4180404e+08 | I8: 8813116 | J8: 2.5061716e+08 | K8: -8813116 | L8: 5.650104e+08 | M8: 1.2038642e+08 | N8: 2.3124675e+08 | O8: 3.5163317e+08 | P8: 2.1337722e+08 | Q8: 0 | R8: 0 | S8: 6580745.8 | T8: 6580745.8 | U8: -6580745.8 | V8: 0 | W8: 0 | X8: 0 | Y8: 0 | Z8: 0 | AA8: 0 | AB8: 0 | AC8: 0 | AD8: 0 | AE8: 0 | AF8: 8.0681444e+08 | AG8: 3.6219046e+08 | AH8: 2.4664061e+08 | AI8: 6.0883108e+08 | AJ8: 1.9798336e+08 | AK8: CAPEX PROJECT FOR CA | AL8: NL-C-CRD-004 | AM8: =VLOOKUP(AL8,Table1[],2,FALSE) -> 718500000 | AN8: =VLOOKUP(AL8,Table1[],3,FALSE) -> 718500000 | AO8: =VLOOKUP($AL8,Table1[],4,FALSE) -> 0 | AP8: =VLOOKUP($AL8,Table1[],5,FALSE) -> 0 | AQ8: =VLOOKUP($AL8,Table1[],6,FALSE) -> 0 | AR8: =VLOOKUP($AL8,Table1[],7,FALSE) -> 0 | AS8: =VLOOKUP($AL8,Table1[],8,FALSE) -> 718500000
A9: 6* Khavda Solar Power P PRJ NL-C-KSP-001 | B9: 398300.04 | C9: 375240 | D9: 23060.04 | E9: 398300.04 | F9: 0 | G9: 375240 | H9: 375240 | I9: 0 | J9: 375240 | K9: 0 | L9: 23060.04 | M9: 0 | N9: 23060.04 | O9: 23060.04 | P9: 0 | Q9: 0 | R9: 0 | S9: 0 | T9: 0 | U9: 0 | V9: 0 | W9: 0 | X9: 0 | Y9: 0 | Z9: 0 | AA9: 0 | AB9: 0 | AC9: 0 | AD9: 0 | AE9: 0 | AF9: 398300.04 | AG9: 375240 | AH9: 23060.04 | AI9: 398300.04 | AJ9: 0 | AK9: Khavda Solar Power P | AL9: NL-C-KSP-001 | AM9: =VLOOKUP(AL9,Table1[],2,FALSE) -> 33358500000 | AN9: =VLOOKUP(AL9,Table1[],3,FALSE) -> 33358500000 | AO9: =VLOOKUP($AL9,Table1[],4,FALSE) -> 0 | AP9: =VLOOKUP($AL9,Table1[],5,FALSE) -> 0 | AQ9: =VLOOKUP($AL9,Table1[],6,FALSE) -> 0 | AR9: =VLOOKUP($AL9,Table1[],7,FALSE) -> 0 | AS9: =VLOOKUP($AL9,Table1[],8,FALSE) -> 33358500000
A10: 6* Land Acquisiton Plan PRJ NL-C-LAQ-001 | B10: 5.4160222e+09 | C10: 3.7048729e+09 | D10: 68131781 | E10: 3.7730047e+09 | F10: 1.6430175e+09 | G10: 2374299156 | H10: 2374299156 | I10: 0 | J10: 2374299156 | K10: 0 | L10: 3.0417231e+09 | M10: 1.3305738e+09 | N10: 68131781 | O10: 1.3987056e+09 | P10: 1.6430175e+09 | Q10: 0 | R10: 0 | S10: 0 | T10: 0 | U10: 0 | V10: 0 | W10: 0 | X10: 0 | Y10: 0 | Z10: 0 | AA10: 0 | AB10: 0 | AC10: 0 | AD10: 0 | AE10: 0 | AF10: 5.4160222e+09 | AG10: 3.7048729e+09 | AH10: 68131781 | AI10: 3.7730047e+09 | AJ10: 1.6430175e+09 | AK10: Land Acquisiton Plan | AL10: NL-C-LAQ-001 | AM10: =VLOOKUP(AL10,Table1[],2,FALSE) -> 1400000000 | AN10: =VLOOKUP(AL10,Table1[],3,FALSE) -> 0 | AO10: =VLOOKUP($AL10,Table1[],4,FALSE) -> 1400000000 | AP10: =VLOOKUP($AL10,Table1[],5,FALSE) -> 0 | AQ10: =VLOOKUP($AL10,Table1[],6,FALSE) -> 0 | AR10: =VLOOKUP($AL10,Table1[],7,FALSE) -> 0 | AS10: =VLOOKUP($AL10,Table1[],8,FALSE) -> 1400000000
A11: 6* EXPANSION OF MINE-IA PRJ NL-C-MIA-001 | B11: 8.8952203e+08 | C11: 6.9805587e+08 | D11: 1.3365458e+08 | E11: 8.3171045e+08 | F11: 57811579 | G11: 3.998401e+08 | H11: 3.9960629e+08 | I11: 0 | J11: 3.9960629e+08 | K11: 233808.46 | L11: 4.8968193e+08 | M11: 2.9844958e+08 | N11: 1.2065071e+08 | O11: 4.1910029e+08 | P11: 70581637 | Q11: 0 | R11: 0 | S11: 13003867 | T11: 13003867 | U11: -13003867 | V11: 0 | W11: 0 | X11: 0 | Y11: 0 | Z11: 0 | AA11: 0 | AB11: 0 | AC11: 0 | AD11: 0 | AE11: 0 | AF11: 8.8952203e+08 | AG11: 6.9805587e+08 | AH11: 1.3365458e+08 | AI11: 8.3171045e+08 | AJ11: 57811579 | AK11: EXPANSION OF MINE-IA | AL11: NL-C-MIA-001 | AM11: =VLOOKUP(AL11,Table1[],2,FALSE) -> 359054495 | AN11: =VLOOKUP(AL11,Table1[],3,FALSE) -> 325589555 | AO11: =VLOOKUP($AL11,Table1[],4,FALSE) -> 33464940 | AP11: =VLOOKUP($AL11,Table1[],5,FALSE) -> 0 | AQ11: =VLOOKUP($AL11,Table1[],6,FALSE) -> 0 | AR11: =VLOOKUP($AL11,Table1[],7,FALSE) -> 0 | AS11: =VLOOKUP($AL11,Table1[],8,FALSE) -> 359054495
A12: 6* Mine 1 Capex Project PRJ NL-C-MN1-001 | B12: 0 | C12: 0 | D12: 0 | E12: 0 | F12: 0 | G12: 0 | H12: 0 | I12: 0 | J12: 0 | K12: 0 | L12: 0 | M12: 0 | N12: 0 | O12: 0 | P12: 0 | Q12: 0 | R12: 0 | S12: 0 | T12: 0 | U12: 0 | V12: 0 | W12: 0 | X12: 0 | Y12: 0 | Z12: 0 | AA12: 0 | AB12: 0 | AC12: 0 | AD12: 0 | AE12: 0 | AF12: 0 | AG12: 0 | AH12: 0 | AI12: 0 | AJ12: 0 | AK12: Mine 1 Capex Project | AL12: NL-C-MN1-001 | AM12: =VLOOKUP(AL12,Table1[],2,FALSE) -> 3390000000 | AN12: =VLOOKUP(AL12,Table1[],3,FALSE) -> 3390000000 | AO12: =VLOOKUP($AL12,Table1[],4,FALSE) -> 0 | AP12: =VLOOKUP($AL12,Table1[],5,FALSE) -> 0 | AQ12: =VLOOKUP($AL12,Table1[],6,FALSE) -> 0 | AR12: =VLOOKUP($AL12,Table1[],7,FALSE) -> 0 | AS12: =VLOOKUP($AL12,Table1[],8,FALSE) -> 3390000000
A13: 6* Mines III Capex Proj PRJ NL-C-MN3-001 | B13: 85900 | C13: 85892.2 | D13: 0 | E13: 85892.2 | F13: 7.8 | G13: 0 | H13: 0 | I13: 0 | J13: 0 | K13: 0 | L13: 85900 | M13: 85892.2 | N13: 0 | O13: 85892.2 | P13: 7.8 | Q13: 0 | R13: 0 | S13: 0 | T13: 0 | U13: 0 | V13: 0 | W13: 0 | X13: 0 | Y13: 0 | Z13: 0 | AA13: 0 | AB13: 0 | AC13: 0 | AD13: 0 | AE13: 0 | AF13: 85900 | AG13: 85892.2 | AH13: 0 | AI13: 85892.2 | AJ13: 7.8 | AK13: Mines III Capex Proj | AL13: NL-C-MN3-001 | AM13: =VLOOKUP(AL13,Table1[],2,FALSE) -> 37557200000 | AN13: =VLOOKUP(AL13,Table1[],3,FALSE) -> 37557200000 | AO13: =VLOOKUP($AL13,Table1[],4,FALSE) -> 0 | AP13: =VLOOKUP($AL13,Table1[],5,FALSE) -> 0 | AQ13: =VLOOKUP($AL13,Table1[],6,FALSE) -> 0 | AR13: =VLOOKUP($AL13,Table1[],7,FALSE) -> 0 | AS13: =VLOOKUP($AL13,Table1[],8,FALSE) -> 37557200000
A14: 6* Talabira II & III OC PRJ NL-C-MTL-001 | B14: 1640000000 | C14: 2.9246923e+09 | D14: 8.2433552e+08 | E14: 3.7490278e+09 | F14: -2.1090278e+09 | G14: 1640000000 | H14: 2.95219e+09 | I14: 8.2419552e+08 | J14: 3.7763855e+09 | K14: -2.1363855e+09 | L14: 0 | M14: -27497693 | N14: 0 | O14: -27497693 | P14: 27497693 | Q14: 0 | R14: 0 | S14: 140000.01 | T14: 140000.01 | U14: -140000.01 | V14: 0 | W14: 0 | X14: 0 | Y14: 0 | Z14: 0 | AA14: 0 | AB14: 0 | AC14: 0 | AD14: 0 | AE14: 0 | AF14: 1640000000 | AG14: 2.9246923e+09 | AH14: 8.2433552e+08 | AI14: 3.7490278e+09 | AJ14: -2.1090278e+09 | AK14: Talabira II & III OC | AL14: NL-C-MTL-001 | AM14: =VLOOKUP(AL14,Table1[],2,FALSE) -> 790000000 | AN14: =VLOOKUP(AL14,Table1[],3,FALSE) -> 790000000 | AO14: =VLOOKUP($AL14,Table1[],4,FALSE) -> 0 | AP14: =VLOOKUP($AL14,Table1[],5,FALSE) -> 0 | AQ14: =VLOOKUP($AL14,Table1[],6,FALSE) -> 0 | AR14: =VLOOKUP($AL14,Table1[],7,FALSE) -> 0 | AS14: =VLOOKUP($AL14,Table1[],8,FALSE) -> 790000000
A15: 6* Talabira II & III OC PRJ NL-C-MTL-002 | B15: 3.2296441e+09 | C15: 4.7821153e+08 | D15: 1.3806956e+09 | E15: 1.8589072e+09 | F15: 1.370737e+09 | G15: 1.0477658e+08 | H15: 93485870 | I15: 0 | J15: 93485870 | K15: 11290713 | L15: 3.1248676e+09 | M15: 3.8472566e+08 | N15: 1.3654743e+09 | O15: 1.7502e+09 | P15: 1.3746676e+09 | Q15: 0 | R15: 0 | S15: 15221329 | T15: 15221329 | U15: -15221329 | V15: 0 | W15: 0 | X15: 0 | Y15: 0 | Z15: 0 | AA15: 0 | AB15: 0 | AC15: 0 | AD15: 0 | AE15: 0 | AF15: 3.2296441e+09 | AG15: 4.7821153e+08 | AH15: 1.3806956e+09 | AI15: 1.8589072e+09 | AJ15: 1.370737e+09 | AK15: Talabira II & III OC | AL15: NL-C-MTL-002 | AM15: =VLOOKUP(AL15,Table1[],2,FALSE) -> 3500000000 | AN15: =VLOOKUP(AL15,Table1[],3,FALSE) -> 1500000000 | AO15: =VLOOKUP($AL15,Table1[],4,FALSE) -> 2000000000 | AP15: =VLOOKUP($AL15,Table1[],5,FALSE) -> 0 | AQ15: =VLOOKUP($AL15,Table1[],6,FALSE) -> 0 | AR15: =VLOOKUP($AL15,Table1[],7,FALSE) -> 0 | AS15: =VLOOKUP($AL15,Table1[],8,FALSE) -> 2700000000
... A411: 6* PSCB Feasibility Pro PRJ NU-F-MPS-001 | B411: 453345000 | C411: 0 | D411: 0 | E411: 0 | F411: 453345000 | G411: 453345000 | H411: 0 | I411: 0 | J411: 0 | K411: 453345000 | L411: 0 | M411: 0 | N411: 0 | O411: 0 | P411: 0 | Q411: 0 | R411: 0 | S411: 0 | T411: 0 | U411: 0 | V411: 0 | W411: 0 | X411: 0 | Y411: 0 | Z411: 0 | AA411: 0 | AB411: 0 | AC411: 0 | AD411: 0 | AE411: 0 | AF411: 453345000 | AG411: 0 | AH411: 0 | AI411: 0 | AJ411: 453345000 | AK411: PSCB Feasibility Pro | AL411: NU-F-MPS-001 | AM411: =VLOOKUP(AL411,Table1[],2,FALSE) -> 1771976000 | AN411: =VLOOKUP(AL411,Table1[],3,FALSE) -> 1771976000 | AO411: =VLOOKUP($AL411,Table1[],4,FALSE) -> 0 | AP411: =VLOOKUP($AL411,Table1[],5,FALSE) -> 0 | AQ411: =VLOOKUP($AL411,Table1[],6,FALSE) -> 0 | AR411: =VLOOKUP($AL411,Table1[],7,FALSE) -> 0 | AS411: =VLOOKUP($AL411,Table1[],8,FALSE) -> 885988000
A420: =B1 -> Total of years
A421: =G1 -> Previous years
A422: =L1 -> 2024
A423: =Q1 -> 2025
A424: =V1 -> 2026
A425: =AA1 -> 2027 and Following
A426: =AF1 -> Overall values

Sheet Actual
A1: ProjectID | B1: Total of years | C1: Previous years | D1: 2024 | E1: 2025 | F1: 2026 | G1: 2027 and Following | H1: Overall values
A2: NL-C-BSP-001 | B2: 17555000001 | C2: 17555000001 | D2: 0 | E2: 0 | F2: 0 | G2: 0 | H2: 17575000001
A3: NL-C-CRD-002 | B3: 5945634 | C3: 5945634 | D3: 0 | E3: 0 | F3: 0 | G3: 0 | H3: 5945634
A4: NL-C-CRD-003 | B4: 18295400 | C4: 18295400 | D4: 0 | E4: 0 | F4: 0 | G4: 0 | H4: 18295400
A5: NL-C-CRD-004 | B5: 718500000 | C5: 718500000 | D5: 0 | E5: 0 | F5: 0 | G5: 0 | H5: 718500000
A6: NL-C-KSP-001 | B6: 33358500000 | C6: 33358500000 | D6: 0 | E6: 0 | F6: 0 | G6: 0 | H6: 33358500000
A7: NL-C-LAQ-001 | B7: 1400000000 | C7: 0 | D7: 1400000000 | E7: 0 | F7: 0 | G7: 0 | H7: 1400000000
A8: NL-C-MIA-001 | B8: 359054495 | C8: 325589555 | D8: 33464940 | E8: 0 | F8: 0 | G8: 0 | H8: 359054495
A9: NL-C-MN1-001 | B9: 3390000000 | C9: 3390000000 | D9: 0 | E9: 0 | F9: 0 | G9: 0 | H9: 3390000000
A10: NL-C-MN3-001 | B10: 37557200000 | C10: 37557200000 | D10: 0 | E10: 0 | F10: 0 | G10: 0 | H10: 37557200000
A11: NL-C-MTL-001 | B11: 790000000 | C11: 790000000 | D11: 0 | E11: 0 | F11: 0 | G11: 0 | H11: 790000000
A12: NL-C-MTL-002 | B12: 3500000000 | C12: 1500000000 | D12: 2000000000 | E12: 0 | F12: 0 | G12: 0 | H12: 2700000000
A13: NL-C-NNT-001 | B13: 3787793152 | C13: 3787793152 | D13: 0 | E13: 0 | F13: 0 | G13: 0 | H13: 11092690297
... A290: NU-F-MPS-001 | B290: 1771976000 | C290: 1771976000 | D290: 0 | E290: 0 | F290: 0 | G290: 0 | H290: 885988000

Sheet Data
A1: Unnamed: 0_level_0_Budget | B1: Total of years_Budget | G1: Previous years_Budget | L1: 2024_Budget | Q1: 2025_Budget | V1: 2026_Budget | AA1: 2027 and Following_Budget | AF1: Overall values_Budget | AK1: ProjectName_Budget | AL1: ProjectID | AM1: Unnamed: 0_level_0_Actual | AN1: Total of years_Actual | AR1: Previous years_Actual | AV1: 2024_Actual | AZ1: 2025_Actual | BD1: 2026_Actual | BH1: 2027 and Following_Actual | BL1: Overall values_Actual | BP1: ProjectName_Actual
A2: Object | B2: Budget | C2: Actual | D2: Commitment | E2: Assigned | F2: Available | G2: Budget | H2: Actual | I2: Commitment | J2: Assigned | K2: Available | L2: Budget | M2: Actual | N2: Commitment | O2: Assigned | P2: Available | Q2: Budget | R2: Actual | S2: Commitment | T2: Assigned | U2: Available | V2: Budget | W2: Actual | X2: Commitment | Y2: Assigned | Z2: Available | AA2: Budget | AB2: Actual | AC2: Commitment | AD2: Assigned | AE2: Available | AF2: Budget | AG2: Actual | AH2: Commitment | AI2: Assigned | AJ2: Available | AM2: Object | AN2: Plan | AO2: Actual | AP2: Variance | AQ2: Var % | AR2: Plan | AS2: Actual | AT2: Variance | AU2: Var % | AV2: Plan | AW2: Actual | AX2: Variance | AY2: Var % | AZ2: Plan | BA2: Actual | BB2: Variance | BC2: Var % | BD2: Plan | BE2: Actual | BF2: Variance | BG2: Var % | BH2: Plan | BI2: Actual | BJ2: Variance | BK2: Var % | BL2: Plan | BM2: Actual | BN2: Variance | BO2: Var %
A3: 6* 600 MW Solar @ GSECL PRJ NG-C-SOL-001 | B3: 0 | C3: 0 | D3: 0 | E3: 0 | F3: 0 | G3: 0 | H3: 0 | I3: 0 | J3: 0 | K3: 0 | L3: 0 | M3: 0 | N3: 0 | O3: 0 | P3: 0 | Q3: 0 | R3: 0 | S3: 0 | T3: 0 | U3: 0 | V3: 0 | W3: 0 | X3: 0 | Y3: 0 | Z3: 0 | AA3: 0 | AB3: 0 | AC3: 0 | AD3: 0 | AE3: 0 | AF3: 0 | AG3: 0 | AH3: 0 | AI3: 0 | AJ3: 0 | AK3: 600 MW Solar @ GSECL | AL3: NG-C-SOL-001
A4: 6* 300 MW Solar Power P PRJ NL-C-BSP-001 | B4: 1.9137258e+10 | C4: 4.6622641e+09 | D4: 1.2756415e+09 | E4: 5.9379056e+09 | F4: 1.3199352e+10 | G4: 1.9527548e+09 | H4: 1.9527548e+09 | I4: 0 | J4: 1.9527548e+09 | K4: 0 | L4: 1.7184503e+10 | M4: 2.7095093e+09 | N4: 1.2756415e+09 | O4: 3.9851508e+09 | P4: 1.3199352e+10 | Q4: 0 | R4: 0 | S4: 0 | T4: 0 | U4: 0 | V4: 0 | W4: 0 | X4: 0 | Y4: 0 | Z4: 0 | AA4: 0 | AB4: 0 | AC4: 0 | AD4: 0 | AE4: 0 | AF4: 1.9137258e+10 | AG4: 4.6622641e+09 | AH4: 1.2756415e+09 | AI4: 5.9379056e+09 | AJ4: 1.3199352e+10 | AK4: 300 MW Solar Power P | AL4: NL-C-BSP-001 | AM4: 6* PRJ NL-C-BSP-001 300 MW Solar Power P | AN4: 17555000001 | AO4: 4662264095 | AP4: 12892735906 | AQ4: 73.4 | AR4: 17555000001 | AS4: 1952754815 | AT4: 15602245186 | AU4: 88.9 | AV4: 0 | AW4: 2709509279 | AX4: -2709509279 | AY4: 0 | AZ4: 0 | BA4: 0 | BB4: 0 | BC4: 0 | BD4: 0 | BE4: 0 | BF4: 0 | BG4: 0 | BH4: 0 | BI4: 0 | BJ4: 0 | BK4: 0 | BL4: 17575000001 | BM4: 4662264095 | BN4: 12912735906 | BO4: 73.5 | BP4: 300 MW Solar Power P
A5: 6* CARD R&D Project PRJ NL-C-CRD-001 | B5: 0 | C5: 0 | D5: 0 | E5: 0 | F5: 0 | G5: 0 | H5: 0 | I5: 0 | J5: 0 | K5: 0 | L5: 0 | M5: 0 | N5: 0 | O5: 0 | P5: 0 | Q5: 0 | R5: 0 | S5: 0 | T5: 0 | U5: 0 | V5: 0 | W5: 0 | X5: 0 | Y5: 0 | Z5: 0 | AA5: 0 | AB5: 0 | AC5: 0 | AD5: 0 | AE5: 0 | AF5: 0 | AG5: 0 | AH5: 0 | AI5: 0 | AJ5: 0 | AK5: CARD R&D Project | AL5: NL-C-CRD-001
A6: 6* Lignite to disel cap PRJ NL-C-CRD-002 | B6: 3987309 | C6: 3987309 | D6: 0 | E6: 3987309 | F6: 0 | G6: 3987309 | H6: 3987309 | I6: 0 | J6: 3987309 | K6: 0 | L6: 0 | M6: 0 | N6: 0 | O6: 0 | P6: 0 | Q6: 0 | R6: 0 | S6: 0 | T6: 0 | U6: 0 | V6: 0 | W6: 0 | X6: 0 | Y6: 0 | Z6: 0 | AA6: 0 | AB6: 0 | AC6: 0 | AD6: 0 | AE6: 0 | AF6: 3987309 | AG6: 3987309 | AH6: 0 | AI6: 3987309 | AJ6: 0 | AK6: Lignite to disel cap | AL6: NL-C-CRD-002 | AM6: 6* PRJ NL-C-CRD-002 Lignite to disel cap | AN6: 5945634 | AO6: 3987309 | AP6: 1958325 | AQ6: 32.9 | AR6: 5945634 | AS6: 3987309 | AT6: 1958325 | AU6: 32.9 | AV6: 0 | AW6: 0 | AX6: 0 | AY6: 0 | AZ6: 0 | BA6: 0 | BB6: 0 | BC6: 0 | BD6: 0 | BE6: 0 | BF6: 0 | BG6: 0 | BH6: 0 | BI6: 0 | BJ6: 0 | BK6: 0 | BL6: 5945634 | BM6: 3987309 | BN6: 1958325 | BO6: 32.9 | BP6: Lignite to disel cap
A7: 6* CARD-IITM-Developmen PRJ NL-C-CRD-003 | B7: 13294999 | C7: 3679142.1 | D7: 9615856.8 | E7: 13294999 | F7: 0 | G7: 13294999 | H7: 3679142.1 | I7: 9615856.8 | J7: 13294999 | K7: 0 | L7: 0 | M7: 0 | N7: 0 | O7: 0 | P7: 0 | Q7: 0 | R7: 0 | S7: 0 | T7: 0 | U7: 0 | V7: 0 | W7: 0 | X7: 0 | Y7: 0 | Z7: 0 | AA7: 0 | AB7: 0 | AC7: 0 | AD7: 0 | AE7: 0 | AF7: 13294999 | AG7: 3679142.1 | AH7: 9615856.8 | AI7: 13294999 | AJ7: 0 | AK7: CARD-IITM-Developmen | AL7: NL-C-CRD-003 | AM7: 6* PRJ NL-C-CRD-003 CARD-IITM-Developmen | AN7: 18295400 | AO7: 3679142 | AP7: 14616258 | AQ7: 79.9 | AR7: 18295400 | AS7: 3679142 | AT7: 14616258 | AU7: 79.9 | AV7: 0 | AW7: 0 | AX7: 0 | AY7: 0 | AZ7: 0 | BA7: 0 | BB7: 0 | BC7: 0 | BD7: 0 | BE7: 0 | BF7: 0 | BG7: 0 | BH7: 0 | BI7: 0 | BJ7: 0 | BK7: 0 | BL7: 18295400 | BM7: 3679142 | BN7: 14616258 | BO7: 79.9 | BP7: CARD-IITM-Developmen
A8: 6* CAPEX PROJECT FOR CA PRJ NL-C-CRD-004 | B8: 8.0681444e+08 | C8: 3.6219046e+08 | D8: 2.4664061e+08 | E8: 6.0883108e+08 | F8: 1.9798336e+08 | G8: 2.4180404e+08 | H8: 2.4180404e+08 | I8: 8813116 | J8: 2.5061716e+08 | K8: -8813116 | L8: 5.650104e+08 | M8: 1.2038642e+08 | N8: 2.3124675e+08 | O8: 3.5163317e+08 | P8: 2.1337722e+08 | Q8: 0 | R8: 0 | S8: 6580745.8 | T8: 6580745.8 | U8: -6580745.8 | V8: 0 | W8: 0 | X8: 0 | Y8: 0 | Z8: 0 | AA8: 0 | AB8: 0 | AC8: 0 | AD8: 0 | AE8: 0 | AF8: 8.0681444e+08 | AG8: 3.6219046e+08 | AH8: 2.4664061e+08 | AI8: 6.0883108e+08 | AJ8: 1.9798336e+08 | AK8: CAPEX PROJECT FOR CA | AL8: NL-C-CRD-004 | AM8: 6* PRJ NL-C-CRD-004 CAPEX PROJECT FOR CA | AN8: 718500000 | AO8: 362190463 | AP8: 356309537 | AQ8: 49.6 | AR8: 718500000 | AS8: 241804043 | AT8: 476695957 | AU8: 66.3 | AV8: 0 | AW8: 120386420 | AX8: -120386420 | AY8: 0 | AZ8: 0 | BA8: 0 | BB8: 0 | BC8: 0 | BD8: 0 | BE8: 0 | BF8: 0 | BG8: 0 | BH8: 0 | BI8: 0 | BJ8: 0 | BK8: 0 | BL8: 718500000 | BM8: 362190463 | BN8: 356309537 | BO8: 49.6 | BP8: CAPEX PROJECT FOR CA
A9: 6* Khavda Solar Power P PRJ NL-C-KSP-001 | B9: 398300.04 | C9: 375240 | D9: 23060.04 | E9: 398300.04 | F9: 0 | G9: 375240 | H9: 375240 | I9: 0 | J9: 375240 | K9: 0 | L9: 23060.04 | M9: 0 | N9: 23060.04 | O9: 23060.04 | P9: 0 | Q9: 0 | R9: 0 | S9: 0 | T9: 0 | U9: 0 | V9: 0 | W9: 0 | X9: 0 | Y9: 0 | Z9: 0 | AA9: 0 | AB9: 0 | AC9: 0 | AD9: 0 | AE9: 0 | AF9: 398300.04 | AG9: 375240 | AH9: 23060.04 | AI9: 398300.04 | AJ9: 0 | AK9: Khavda Solar Power P | AL9: NL-C-KSP-001 | AM9: 6* PRJ NL-C-KSP-001 Khavda Solar Power P | AN9: 33358500000 | AO9: 375240 | AP9: 33358124760 | AQ9: 100 | AR9: 33358500000 | AS9: 375240 | AT9: 33358124760 | AU9: 100 | AV9: 0 | AW9: 0 | AX9: 0 | AY9: 0 | AZ9: 0 | BA9: 0 | BB9: 0 | BC9: 0 | BD9: 0 | BE9: 0 | BF9: 0 | BG9: 0 | BH9: 0 | BI9: 0 | BJ9: 0 | BK9: 0 | BL9: 33358500000 | BM9: 375240 | BN9: 33358124760 | BO9: 100 | BP9: Khavda Solar Power P
A10: 6* Land Acquisiton Plan PRJ NL-C-LAQ-001 | B10: 5.4160222e+09 | C10: 3.7048729e+09 | D10: 68131781 | E10: 3.7730047e+09 | F10: 1.6430175e+09 | G10: 2374299156 | H10: 2374299156 | I10: 0 | J10: 2374299156 | K10: 0 | L10: 3.0417231e+09 | M10: 1.3305738e+09 | N10: 68131781 | O10: 1.3987056e+09 | P10: 1.6430175e+09 | Q10: 0 | R10: 0 | S10: 0 | T10: 0 | U10: 0 | V10: 0 | W10: 0 | X10: 0 | Y10: 0 | Z10: 0 | AA10: 0 | AB10: 0 | AC10: 0 | AD10: 0 | AE10: 0 | AF10: 5.4160222e+09 | AG10: 3.7048729e+09 | AH10: 68131781 | AI10: 3.7730047e+09 | AJ10: 1.6430175e+09 | AK10: Land Acquisiton Plan | AL10: NL-C-LAQ-001 | AM10: 6* PRJ NL-C-LAQ-001 Land Acquisiton Plan | AN10: 1400000000 | AO10: 3704872940 | AP10: -2304872940 | AQ10: -164.6 | AR10: 0 | AS10: 2374299156 | AT10: -2374299156 | AU10: 0 | AV10: 1400000000 | AW10: 1330573784 | AX10: 69426216 | AY10: 5 | AZ10: 0 | BA10: 0 | BB10: 0 | BC10: 0 | BD10: 0 | BE10: 0 | BF10: 0 | BG10: 0 | BH10: 0 | BI10: 0 | BJ10: 0 | BK10: 0 | BL10: 1400000000 | BM10: 3704872940 | BN10: -2304872940 | BO10: -164.6 | BP10: Land Acquisiton Plan
A11: 6* EXPANSION OF MINE-IA PRJ NL-C-MIA-001 | B11: 8.8952203e+08 | C11: 6.9805587e+08 | D11: 1.3365458e+08 | E11: 8.3171045e+08 | F11: 57811579 | G11: 3.998401e+08 | H11: 3.9960629e+08 | I11: 0 | J11: 3.9960629e+08 | K11: 233808.46 | L11: 4.8968193e+08 | M11: 2.9844958e+08 | N11: 1.2065071e+08 | O11: 4.1910029e+08 | P11: 70581637 | Q11: 0 | R11: 0 | S11: 13003867 | T11: 13003867 | U11: -13003867 | V11: 0 | W11: 0 | X11: 0 | Y11: 0 | Z11: 0 | AA11: 0 | AB11: 0 | AC11: 0 | AD11: 0 | AE11: 0 | AF11: 8.8952203e+08 | AG11: 6.9805587e+08 | AH11: 1.3365458e+08 | AI11: 8.3171045e+08 | AJ11: 57811579 | AK11: EXPANSION OF MINE-IA | AL11: NL-C-MIA-001 | AM11: 6* PRJ NL-C-MIA-001 EXPANSION OF MINE-IA | AN11: 359054495 | AO11: 698055871 | AP11: -339001376 | AQ11: -94.4 | AR11: 325589555 | AS11: 399606292 | AT11: -74016737 | AU11: -22.7 | AV11: 33464940 | AW11: 298449579 | AX11: -264984639 | AY11: -791.8 | AZ11: 0 | BA11: 0 | BB11: 0 | BC11: 0 | BD11: 0 | BE11: 0 | BF11: 0 | BG11: 0 | BH11: 0 | BI11: 0 | BJ11: 0 | BK11: 0 | BL11: 359054495 | BM11: 698055871 | BN11: -339001376 | BO11: -94.4 | BP11: EXPANSION OF MINE-IA
A12: 6* Mine 1 Capex Project PRJ NL-C-MN1-001 | B12: 0 | C12: 0 | D12: 0 | E12: 0 | F12: 0 | G12: 0 | H12: 0 | I12: 0 | J12: 0 | K12: 0 | L12: 0 | M12: 0 | N12: 0 | O12: 0 | P12: 0 | Q12: 0 | R12: 0 | S12: 0 | T12: 0 | U12: 0 | V12: 0 | W12: 0 | X12: 0 | Y12: 0 | Z12: 0 | AA12: 0 | AB12: 0 | AC12: 0 | AD12: 0 | AE12: 0 | AF12: 0 | AG12: 0 | AH12: 0 | AI12: 0 | AJ12: 0 | AK12: Mine 1 Capex Project | AL12: NL-C-MN1-001 | AM12: 6* PRJ NL-C-MN1-001 Mine 1 Capex Project | AN12: 3390000000 | AO12: 0 | AP12: 3390000000 | AQ12: 100 | AR12: 3390000000 | AS12: 0 | AT12: 3390000000 | AU12: 100 | AV12: 0 | AW12: 0 | AX12: 0 | AY12: 0 | AZ12: 0 | BA12: 0 | BB12: 0 | BC12: 0 | BD12: 0 | BE12: 0 | BF12: 0 | BG12: 0 | BH12: 0 | BI12: 0 | BJ12: 0 | BK12: 0 | BL12: 3390000000 | BM12: 0 | BN12: 3390000000 | BO12: 100 | BP12: Mine 1 Capex Project
A13: 6* Mines III Capex Proj PRJ NL-C-MN3-001 | B13: 85900 | C13: 85892.2 | D13: 0 | E13: 85892.2 | F13: 7.8 | G13: 0 | H13: 0 | I13: 0 | J13: 0 | K13: 0 | L13: 85900 | M13: 85892.2 | N13: 0 | O13: 85892.2 | P13: 7.8 | Q13: 0 | R13: 0 | S13: 0 | T13: 0 | U13: 0 | V13: 0 | W13: 0 | X13: 0 | Y13: 0 | Z13: 0 | AA13: 0 | AB13: 0 | AC13: 0 | AD13: 0 | AE13: 0 | AF13: 85900 | AG13: 85892.2 | AH13: 0 | AI13: 85892.2 | AJ13: 7.8 | AK13: Mines III Capex Proj | AL13: NL-C-MN3-001 | AM13: 6* PRJ NL-C-MN3-001 Mines III Capex Proj | AN13: 37557200000 | AO13: 85892 | AP13: 37557114108 | AQ13: 100 | AR13: 37557200000 | AS13: 0 | AT13: 37557200000 | AU13: 100 | AV13: 0 | AW13: 85892 | AX13: -85892 | AY13: 0 | AZ13: 0 | BA13: 0 | BB13: 0 | BC13: 0 | BD13: 0 | BE13: 0 | BF13: 0 | BG13: 0 | BH13: 0 | BI13: 0 | BJ13: 0 | BK13: 0 | BL13: 37557200000 | BM13: 85892 | BN13: 37557114108 | BO13: 100 | BP13: Mines III Capex Proj
A14: 6* Talabira II & III OC PRJ NL-C-MTL-001 | B14: 1640000000 | C14: 2.9246923e+09 | D14: 8.2433552e+08 | E14: 3.7490278e+09 | F14: -2.1090278e+09 | G14: 1640000000 | H14: 2.95219e+09 | I14: 8.2419552e+08 | J14: 3.7763855e+09 | K14: -2.1363855e+09 | L14: 0 | M14: -27497693 | N14: 0 | O14: -27497693 | P14: 27497693 | Q14: 0 | R14: 0 | S14: 140000.01 | T14: 140000.01 | U14: -140000.01 | V14: 0 | W14: 0 | X14: 0 | Y14: 0 | Z14: 0 | AA14: 0 | AB14: 0 | AC14: 0 | AD14: 0 | AE14: 0 | AF14: 1640000000 | AG14: 2.9246923e+09 | AH14: 8.2433552e+08 | AI14: 3.7490278e+09 | AJ14: -2.1090278e+09 | AK14: Talabira II & III OC | AL14: NL-C-MTL-001 | AM14: 6* PRJ NL-C-MTL-001 Talabira II & III OC | AN14: 790000000 | AO14: 2924692278 | AP14: -2134692278 | AQ14: -270.2 | AR14: 790000000 | AS14: 2952189971 | AT14: -2162189971 | AU14: -273.7 | AV14: 0 | AW14: -27497693 | AX14: 27497693 | AY14: 0 | AZ14: 0 | BA14: 0 | BB14: 0 | BC14: 0 | BD14: 0 | BE14: 0 | BF14: 0 | BG14: 0 | BH14: 0 | BI14: 0 | BJ14: 0 | BK14: 0 | BL14: 790000000 | BM14: 2924692278 | BN14: -2134692278 | BO14: -270.2 | BP14: Talabira II & III OC
A15: 6* Talabira II & III OC PRJ NL-C-MTL-002 | B15: 3.2296441e+09 | C15: 4.7821153e+08 | D15: 1.3806956e+09 | E15: 1.8589072e+09 | F15: 1.370737e+09 | G15: 1.0477658e+08 | H15: 93485870 | I15: 0 | J15: 93485870 | K15: 11290713 | L15: 3.1248676e+09 | M15: 3.8472566e+08 | N15: 1.3654743e+09 | O15: 1.7502e+09 | P15: 1.3746676e+09 | Q15: 0 | R15: 0 | S15: 15221329 | T15: 15221329 | U15: -15221329 | V15: 0 | W15: 0 | X15: 0 | Y15: 0 | Z15: 0 | AA15: 0 | AB15: 0 | AC15: 0 | AD15: 0 | AE15: 0 | AF15: 3.2296441e+09 | AG15: 4.7821153e+08 | AH15: 1.3806956e+09 | AI15: 1.8589072e+09 | AJ15: 1.370737e+09 | AK15: Talabira II & III OC | AL15: NL-C-MTL-002 | AM15: 6* PRJ NL-C-MTL-002 Talabira II & III OC | AN15: 3500000000 | AO15: 478211532 | AP15: 3021788468 | AQ15: 86.3 | AR15: 1500000000 | AS15: 93485870 | AT15: 1406514130 | AU15: 93.8 | AV15: 2000000000 | AW15: 384725662 | AX15: 1615274338 | AY15: 80.8 | AZ15: 0 | BA15: 0 | BB15: 0 | BC15: 0 | BD15: 0 | BE15: 0 | BF15: 0 | BG15: 0 | BH15: 0 | BI15: 0 | BJ15: 0 | BK15: 0 | BL15: 2700000000 | BM15: 478211532 | BN15: 2221788468 | BO15: 82.3 | BP15: Talabira II & III OC
A16: 6* NNTPP CAPEX PROJECT PRJ NL-C-NNT-001 | B16: 2120002000 | C16: 8.3684787e+08 | D16: 1.0860058e+09 | E16: 1.9228537e+09 | F16: 1.971483e+08 | G16: 8.3649597e+08 | H16: 8.3164968e+08 | I16: 0 | J16: 8.3164968e+08 | K16: 4846283.9 | L16: 1.283506e+09 | M16: 5198186.4 | N16: 1.0860058e+09 | O16: 1.091204e+09 | P16: 1.9230201e+08 | Q16: 0 | R16: 0 | S16: 0 | T16: 0 | U16: 0 | V16: 0 | W16: 0 | X16: 0 | Y16: 0 | Z16: 0 | AA16: 0 | AB16: 0 | AC16: 0 | AD16: 0 | AE16: 0 | AF16: 2120002000 | AG16: 8.3684787e+08 | AH16: 1.0860058e+09 | AI16: 1.9228537e+09 | AJ16: 1.971483e+08 | AK16: NNTPP CAPEX PROJECT | AL16: NL-C-NNT-001 | AM16: 6* PRJ NL-C-NNT-001 NNTPP CAPEX PROJECT | AN16: 3787793152 | AO16: 836847870 | AP16: 2950945281 | AQ16: 77.9 | AR16: 3787793152 | AS16: 831649684 | AT16: 2956143468 | AU16: 78 | AV16: 0 | AW16: 5198186 | AX16: -5198186 | AY16: 0 | AZ16: 0 | BA16: 0 | BB16: 0 | BC16: 0 | BD16: 0 | BE16: 0 | BF16: 0 | BG16: 0 | BH16: 0 | BI16: 0 | BJ16: 0 | BK16: 0 | BL16: 11092690297 | BM16: 836847870 | BN16: 10255842426 | BO16: 92.5 | BP16: NNTPP CAPEX PROJECT
A17: 6* NNTPP Flue Gas Desul PRJ NL-C-NNT-002 | B17: 1.0651836e+10 | C17: 9.4673189e+09 | D17: 1.122297e+09 | E17: 1.0589616e+10 | F17: 62220520 | G17: 6.3930374e+09 | H17: 6.6446558e+09 | I17: 40616473 | J17: 6.6852723e+09 | K17: -2.9223484e+08 | L17: 4.2587989e+09 | M17: 2.8226631e+09 | N17: 1.0816805e+09 | O17: 3.9043436e+09 | P17: 3.5445536e+08 | Q17: 0 | R17: 0 | S17: 0 | T17: 0 | U17: 0 | V17: 0 | W17: 0 | X17: 0 | Y17: 0 | Z17: 0 | AA17: 0 | AB17: 0 | AC17: 0 | AD17: 0 | AE17: 0 | AF17: 1.0651836e+10 | AG17: 9.4673189e+09 | AH17: 1.122297e+09 | AI17: 1.0589616e+10 | AJ17: 62220520 | AK17: NNTPP Flue Gas Desul | AL17: NL-C-NNT-002 | AM17: 6* PRJ NL-C-NNT-002 NNTPP Flue Gas Desul | AN17: 1162278 | AO17: 9467318888 | AP17: -9466156610 | AQ17: -814448.6 | AR17: 1162278 | AS17: 6644655814 | AT17: -6643493536 | AU17: -571592.5 | AV17: 0 | AW17: 2822663073 | AX17: -2822663073 | AY17: 0 | AZ17: 0 | BA17: 0 | BB17: 0 | BC17: 0 | BD17: 0 | BE17: 0 | BF17: 0 | BG17: 0 | BH17: 0 | BI17: 0 | BJ17: 0 | BK17: 0 | BL17: 9148902993 | BM17: 9467318888 | BN17: -318415895 | BO17: -3.5 | BP17: NNTPP Flue Gas Desul
A18: 6* New Patrapara South PRJ NL-C-NPS-001 | B18: 2400000000 | C18: 1.9579273e+09 | D18: 0 | E18: 1.9579273e+09 | F18: 4.4207268e+08 | G18: 0 | H18: 0 | I18: 0 | J18: 0 | K18: 0 | L18: 2400000000 | M18: 1.9579273e+09 | N18: 0 | O18: 1.9579273e+09 | P18: 4.4207268e+08 | Q18: 0 | R18: 0 | S18: 0 | T18: 0 | U18: 0 | V18: 0 | W18: 0 | X18: 0 | Y18: 0 | Z18: 0 | AA18: 0 | AB18: 0 | AC18: 0 | AD18: 0 | AE18: 0 | AF18: 2400000000 | AG18: 1.9579273e+09 | AH18: 0 | AI18: 1.9579273e+09 | AJ18: 4.4207268e+08 | AK18: New Patrapara South | AL18: NL-C-NPS-001 | AM18: 6* PRJ NL-C-NPS-001 New Patrapara South | AN18: 4805000000 | AO18: 1957927320 | AP18: 2847072680 | AQ18: 59.3 | AR18: 0 | AS18: 0 | AT18: 0 | AU18: 0 | AV18: 4805000000 | AW18: 1957927320 | AX18: 2847072680 | AY18: 59.3 | AZ18: 0 | BA18: 0 | BB18: 0 | BC18: 0 | BD18: 0 | BE18: 0 | BF18: 0 | BG18: 0 | BH18: 0 | BI18: 0 | BJ18: 0 | BK18: 0 | BL18: 4805000000 | BM18: 1957927320 | BN18: 2847072680 | BO18: 59.3 | BP18: New Patrapara South
A19: 6* IREDA-CPSU Scheme Ph PRJ NL-C-PBD-001 | B19: 60180000 | C19: 0 | D19: 0 | E19: 0 | F19: 60180000 | G19: 0 | H19: 0 | I19: 0 | J19: 0 | K19: 0 | L19: 60180000 | M19: 0 | N19: 0 | O19: 0 | P19: 60180000 | Q19: 0 | R19: 0 | S19: 0 | T19: 0 | U19: 0 | V19: 0 | W19: 0 | X19: 0 | Y19: 0 | Z19: 0 | AA19: 0 | AB19: 0 | AC19: 0 | AD19: 0 | AE19: 0 | AF19: 60180000 | AG19: 0 | AH19: 0 | AI19: 0 | AJ19: 60180000 | AK19: IREDA-CPSU Scheme Ph | AL19: NL-C-PBD-001
A20: 6* Neyveli 2x65 MW Sola PRJ NL-C-PBD-002 | B20: 10669830 | C20: 10289078 | D20: 380751.03 | E20: 10669829 | F20: 0.96 | G20: 0 | H20: 10289078 | I20: 0 | J20: 10289078 | K20: -10289078 | L20: 10669830 | M20: 0 | N20: 380751.03 | O20: 380751.03 | P20: 10289079 | Q20: 0 | R20: 0 | S20: 0 | T20: 0 | U20: 0 | V20: 0 | W20: 0 | X20: 0 | Y20: 0 | Z20: 0 | AA20: 0 | AB20: 0 | AC20: 0 | AD20: 0 | AE20: 0 | AF20: 10669830 | AG20: 10289078 | AH20: 380751.03 | AI20: 10669829 | AJ20: 0.96 | AK20: Neyveli 2x65 MW Sola | AL20: NL-C-PBD-002 | AM20: 6* PRJ NL-C-PBD-002 Neyveli 2x65 MW Sola | AN20: 6669830 | AO20: 10289078 | AP20: -3619248 | AQ20: -54.3 | AR20: 6669830 | AS20: 10289078 | AT20: -3619248 | AU20: -54.3 | AV20: 0 | AW20: 0 | AX20: 0 | AY20: 0 | AZ20: 0 | BA20: 0 | BB20: 0 | BC20: 0 | BD20: 0 | BE20: 0 | BF20: 0 | BG20: 0 | BH20: 0 | BI20: 0 | BJ20: 0 | BK20: 0 | BL20: 10669830 | BM20: 10289078 | BN20: 380752 | BO20: 3.6 | BP20: Neyveli 2x65 MW Sola
A21: 6* Solar 10 MW Power Pr PRJ NL-C-SOL-001 | B21: 175000000 | C21: 4.5359629e+08 | D21: 1.4450137e+08 | E21: 5.9809767e+08 | F21: -4.2309767e+08 | G21: 175000000 | H21: 4.5359629e+08 | I21: 0 | J21: 4.5359629e+08 | K21: -2.7859629e+08 | L21: 0 | M21: 0 | N21: 1.4450137e+08 | O21: 1.4450137e+08 | P21: -1.4450137e+08 | Q21: 0 | R21: 0 | S21: 0 | T21: 0 | U21: 0 | V21: 0 | W21: 0 | X21: 0 | Y21: 0 | Z21: 0 | AA21: 0 | AB21: 0 | AC21: 0 | AD21: 0 | AE21: 0 | AF21: 175000000 | AG21: 4.5359629e+08 | AH21: 1.4450137e+08 | AI21: 5.9809767e+08 | AJ21: -4.2309767e+08 | AK21: Solar 10 MW Power Pr | AL21: NL-C-SOL-001 | AM21: 6* PRJ NL-C-SOL-001 Solar 10 MW Power Pr | AN21: 0 | AO21: 453596292 | AP21: -453596292 | AQ21: 0 | AR21: 0 | AS21: 453596292 | AT21: -453596292 | AU21: 0 | AV21: 0 | AW21: 0 | AX21: 0 | AY21: 0 | AZ21: 0 | BA21: 0 | BB21: 0 | BC21: 0 | BD21: 0 | BE21: 0 | BF21: 0 | BG21: 0 | BH21: 0 | BI21: 0 | BJ21: 0 | BK21: 0 | BL21: 0 | BM21: 453596292 | BN21: -453596292 | BO21: 0 | BP21: Solar 10 MW Power Pr
A22: 6* Solar 50 MW in Mine PRJ NL-C-SOL-002 | B22: 1807443528 | C22: 1.2545294e+09 | D22: 5.5289682e+08 | E22: 1.8074262e+09 | F22: 17288.72 | G22: 850544 | H22: 850544 | I22: 0 | J22: 850544 | K22: 0 | L22: 1806592984 | M22: 1.2536789e+09 | N22: 5.5289682e+08 | O22: 1.8065757e+09 | P22: 17288.72 | Q22: 0 | R22: 0 | S22: 0 | T22: 0 | U22: 0 | V22: 0 | W22: 0 | X22: 0 | Y22: 0 | Z22: 0 | AA22: 0 | AB22: 0 | AC22: 0 | AD22: 0 | AE22: 0 | AF22: 1807443528 | AG22: 1.2545294e+09 | AH22: 5.5289682e+08 | AI22: 1.8074262e+09 | AJ22: 17288.72 | AK22: Solar 50 MW in Mine | AL22: NL-C-SOL-002 | AM22: 6* PRJ NL-C-SOL-002 Solar 50 MW in Mine | AN22: 2951200000 | AO22: 1254529420 | AP22: 1696670580 | AQ22: 57.5 | AR22: 2951200000 | AS22: 850544 | AT22: 2950349456 | AU22: 100 | AV22: 0 | AW22: 1253678876 | AX22: -1253678876 | AY22: 0 | AZ22: 0 | BA22: 0 | BB22: 0 | BC22: 0 | BD22: 0 | BE22: 0 | BF22: 0 | BG22: 0 | BH22: 0 | BI22: 0 | BJ22: 0 | BK22: 0 | BL22: 2951200000 | BM22: 1254529420 | BN22: 1696670580 | BO22: 57.5 | BP22: Solar 50 MW in Mine
A23: 6* 200 MW Solar Power G PRJ NL-C-SOL-003 | B23: 522382455 | C23: 1420211.2 | D23: 902748.88 | E23: 2322960 | F23: 5.2005949e+08 | G23: 0 | H23: 0 | I23: 0 | J23: 0 | K23: 0 | L23: 522382455 | M23: 1420211.2 | N23: 902748.88 | O23: 2322960 | P23: 5.2005949e+08 | Q23: 0 | R23: 0 | S23: 0 | T23: 0 | U23: 0 | V23: 0 | W23: 0 | X23: 0 | Y23: 0 | Z23: 0 | AA23: 0 | AB23: 0 | AC23: 0 | AD23: 0 | AE23: 0 | AF23: 522382455 | AG23: 1420211.2 | AH23: 902748.88 | AI23: 2322960 | AJ23: 5.2005949e+08 | AK23: 200 MW Solar Power G | AL23: NL-C-SOL-003 | AM23: 6* PRJ NL-C-SOL-003 200 MW Solar Power G | AN23: 12138960364 | AO23: 1420211 | AP23: 12137540152 | AQ23: 100 | AR23: 0 | AS23: 0 | AT23: 0 | AU23: 0 | AV23: 12138960364 | AW23: 1420211 | AX23: 12137540152 | AY23: 100 | AZ23: 0 | BA23: 0 | BB23: 0 | BC23: 0 | BD23: 0 | BE23: 0 | BF23: 0 | BG23: 0 | BH23: 0 | BI23: 0 | BJ23: 0 | BK23: 0 | BL23: 12138960364 | BM23: 1420211 | BN23: 12137540152 | BO23: 100 | BP23: 200 MW Solar Power G
A24: 6* 100 MW SOLAR (HYBRID PRJ NL-C-SOL-004 | B24: 1350000000 | C24: 1176000 | D24: 574000 | E24: 1750000 | F24: 1348250000 | G24: 0 | H24: 0 | I24: 0 | J24: 0 | K24: 0 | L24: 1350000000 | M24: 1176000 | N24: 574000 | O24: 1750000 | P24: 1348250000 | Q24: 0 | R24: 0 | S24: 0 | T24: 0 | U24: 0 | V24: 0 | W24: 0 | X24: 0 | Y24: 0 | Z24: 0 | AA24: 0 | AB24: 0 | AC24: 0 | AD24: 0 | AE24: 0 | AF24: 1350000000 | AG24: 1176000 | AH24: 574000 | AI24: 1750000 | AJ24: 1348250000 | AK24: 100 MW SOLAR (HYBRID | AL24: NL-C-SOL-004 | AM24: 6* PRJ NL-C-SOL-004 100 MW SOLAR (HYBRID | AN24: 0 | AO24: 1176000 | AP24: -1176000 | AQ24: 0 | AR24: 0 | AS24: 0 | AT24: 0 | AU24: 0 | AV24: 0 | AW24: 1176000 | AX24: -1176000 | AY24: 0 | AZ24: 0 | BA24: 0 | BB24: 0 | BC24: 0 | BD24: 0 | BE24: 0 | BF24: 0 | BG24: 0 | BH24: 0 | BI24: 0 | BJ24: 0 | BK24: 0 | BL24: 0 | BM24: 1176000 | BN24: -1176000 | BO24: 0 | BP24: 100 MW SOLAR (HYBRID
A25: 6* TPS2 Second Expansio PRJ NL-C-T22-001 | B25: 37386465 | C25: 45813963 | D25: 1018104 | E25: 46832067 | F25: -9445602 | G25: 28694848 | H25: 38047111 | I25: 0 | J25: 38047111 | K25: -9352262.8 | L25: 8691616.8 | M25: 7766852 | N25: 1018104 | O25: 8784956 | P25: -93339.24 | Q25: 0 | R25: 0 | S25: 0 | T25: 0 | U25: 0 | V25: 0 | W25: 0 | X25: 0 | Y25: 0 | Z25: 0 | AA25: 0 | AB25: 0 | AC25: 0 | AD25: 0 | AE25: 0 | AF25: 37386465 | AG25: 45813963 | AH25: 1018104 | AI25: 46832067 | AJ25: -9445602 | AK25: TPS2 Second Expansio | AL25: NL-C-T22-001 | AM25: 6* PRJ NL-C-T22-001 TPS2 Second Expansio | AN25: 668500000 | AO25: 45813963 | AP25: 622686037 | AQ25: 93.1 | AR25: 668500000 | AS25: 38047111 | AT25: 630452889 | AU25: 94.3 | AV25: 0 | AW25: 7766852 | AX25: -7766852 | AY25: 0 | AZ25: 0 | BA25: 0 | BB25: 0 | BC25: 0 | BD25: 0 | BE25: 0 | BF25: 0 | BG25: 0 | BH25: 0 | BI25: 0 | BJ25: 0 | BK25: 0 | BL25: 668500000 | BM25: 45813963 | BN25: 622686037 | BO25: 93.1 | BP25: TPS2 Second Expansio
A26: 6* Performance Improvem PRJ NL-C-T2E-001 | B26: 1058534096 | C26: 7.8493291e+08 | D26: 2.1141268e+08 | E26: 9.9634559e+08 | F26: 62188509 | G26: 5.4729204e+08 | H26: 5.4729204e+08 | I26: 0 | J26: 5.4729204e+08 | K26: 0 | L26: 5.1124205e+08 | M26: 2.3764087e+08 | N26: 2.1141268e+08 | O26: 4.4905354e+08 | P26: 62188509 | Q26: 0 | R26: 0 | S26: 0 | T26: 0 | U26: 0 | V26: 0 | W26: 0 | X26: 0 | Y26: 0 | Z26: 0 | AA26: 0 | AB26: 0 | AC26: 0 | AD26: 0 | AE26: 0 | AF26: 1058534096 | AG26: 7.8493291e+08 | AH26: 2.1141268e+08 | AI26: 9.9634559e+08 | AJ26: 62188509 | AK26: Performance Improvem | AL26: NL-C-T2E-001 | AM26: 6* PRJ NL-C-T2E-001 Performance Improvem | AN26: 1058534096 | AO26: 784932908 | AP26: 273601188 | AQ26: 25.8 | AR26: 1058534096 | AS26: 547292043 | AT26: 511242053 | AU26: 48.3 | AV26: 0 | AW26: 237640865 | AX26: -237640865 | AY26: 0 | AZ26: 0 | BA26: 0 | BB26: 0 | BC26: 0 | BD26: 0 | BE26: 0 | BF26: 0 | BG26: 0 | BH26: 0 | BI26: 0 | BJ26: 0 | BK26: 0 | BL26: 1058534096 | BM26: 784932908 | BN26: 273601188 | BO26: 25.8 | BP26: Performance Improvem
A27: 6* Mini Smart City PRJ NL-C-TAA-001 | B27: 173380000 | C27: 6139687.5 | D27: 5321062.5 | E27: 11460750 | F27: 161919250 | G27: 2455875 | H27: 2455875 | I27: 0 | J27: 2455875 | K27: 0 | L27: 170924125 | M27: 3683812.5 | N27: 5321062.5 | O27: 9004875 | P27: 161919250 | Q27: 0 | R27: 0 | S27: 0 | T27: 0 | U27: 0 | V27: 0 | W27: 0 | X27: 0 | Y27: 0 | Z27: 0 | AA27: 0 | AB27: 0 | AC27: 0 | AD27: 0 | AE27: 0 | AF27: 173380000 | AG27: 6139687.5 | AH27: 5321062.5 | AI27: 11460750 | AJ27: 161919250 | AK27: Mini Smart City | AL27: NL-C-TAA-001 | AM27: 6* PRJ NL-C-TAA-001 Mini Smart City | AN27: 6720 | AO27: 6139688 | AP27: -6132968 | AQ27: -91271.2 | AR27: 6720 | AS27: 2455875 | AT27: -2449156 | AU27: -36448.5 | AV27: 0 | AW27: 3683813 | AX27: -3683813 | AY27: 0 | AZ27: 0 | BA27: 0 | BB27: 0 | BC27: 0 | BD27: 0 | BE27: 0 | BF27: 0 | BG27: 0 | BH27: 0 | BI27: 0 | BJ27: 0 | BK27: 0 | BL27: 6551 | BM27: 6139688 | BN27: -6133137 | BO27: -93624.2 | BP27: Mini Smart City
A28: 6* NLC Talabira Thermal PRJ NL-C-TPP-001 | B28: 4.2282451e+09 | C28: 1.4718109e+09 | D28: 1.3161227e+09 | E28: 2.7879336e+09 | F28: 1.4403115e+09 | G28: 1.0036764e+09 | H28: 1.0048295e+09 | I28: 0 | J28: 1.0048295e+09 | K28: -1153049.4 | L28: 3.2245687e+09 | M28: 4.6698144e+08 | N28: 1.3161227e+09 | O28: 1.7831041e+09 | P28: 1.4414646e+09 | Q28: 0 | R28: 0 | S28: 0 | T28: 0 | U28: 0 | V28: 0 | W28: 0 | X28: 0 | Y28: 0 | Z28: 0 | AA28: 0 | AB28: 0 | AC28: 0 | AD28: 0 | AE28: 0 | AF28: 4.2282451e+09 | AG28: 1.4718109e+09 | AH28: 1.3161227e+09 | AI28: 2.7879336e+09 | AJ28: 1.4403115e+09 | AK28: NLC Talabira Thermal | AL28: NL-C-TPP-001 | AM28: 6* PRJ NL-C-TPP-001 NLC Talabira Thermal | AN28: 12542700000 | AO28: 1471810906 | AP28: 11070889094 | AQ28: 88.3 | AR28: 11542700000 | AS28: 1004829466 | AT28: 10537870534 | AU28: 91.3 | AV28: 1000000000 | AW28: 466981440 | AX28: 533018560 | AY28: 53.3 | AZ28: 0 | BA28: 0 | BB28: 0 | BC28: 0 | BD28: 0 | BE28: 0 | BF28: 0 | BG28: 0 | BH28: 0 | BI28: 0 | BJ28: 0 | BK28: 0 | BL28: 11542700000 | BM28: 1471810906 | BN28: 10070889094 | BO28: 87.2 | BP28: NLC Talabira Thermal
A29: 6* NLC TTPP Main Packag PRJ NL-C-TPP-002 | B29: 6029690000 | C29: 1529689520 | D29: 4.4659793e+09 | E29: 5.9956688e+09 | F29: 34021226 | G29: 1529689520 | H29: 1529689520 | I29: 0 | J29: 1529689520 | K29: 0 | L29: 4500000480 | M29: 0 | N29: 4.4659793e+09 | O29: 4.4659793e+09 | P29: 34021226 | Q29: 0 | R29: 0 | S29: 0 | T29: 0 | U29: 0 | V29: 0 | W29: 0 | X29: 0 | Y29: 0 | Z29: 0 | AA29: 0 | AB29: 0 | AC29: 0 | AD29: 0 | AE29: 0 | AF29: 6029690000 | AG29: 1529689520 | AH29: 4.4659793e+09 | AI29: 5.9956688e+09 | AJ29: 34021226 | AK29: NLC TTPP Main Packag | AL29: NL-C-TPP-002 | AM29: 6* PRJ NL-C-TPP-002 NLC TTPP Main Packag | AN29: 0 | AO29: 1529689520 | AP29: -1529689520 | AQ29: 0 | AR29: 0 | AS29: 1529689520 | AT29: -1529689520 | AU29: 0 | AV29: 0 | AW29: 0 | AX29: 0 | AY29: 0 | AZ29: 0 | BA29: 0 | BB29: 0 | BC29: 0 | BD29: 0 | BE29: 0 | BF29: 0 | BG29: 0 | BH29: 0 | BI29: 0 | BJ29: 0 | BK29: 0 | BL29: 0 | BM29: 1529689520 | BN29: -1529689520 | BO29: 0 | BP29: NLC TTPP Main Packag
A30: 6* TS I Switchyard Modi PRJ NL-C-TS1-001 | B30: 3.1061295e+08 | C30: 2.8340981e+08 | D30: 27197650 | E30: 3.1060746e+08 | F30: 5491.19 | G30: 2.5797312e+08 | H30: 2.5797312e+08 | I30: 0.59 | J30: 2.5797313e+08 | K30: -0.59 | L30: 52639823 | M30: 25436681 | N30: 27197650 | O30: 52634331 | P30: 5491.78 | Q30: 0 | R30: 0 | S30: 0 | T30: 0 | U30: 0 | V30: 0 | W30: 0 | X30: 0 | Y30: 0 | Z30: 0 | AA30: 0 | AB30: 0 | AC30: 0 | AD30: 0 | AE30: 0 | AF30: 3.1061295e+08 | AG30: 2.8340981e+08 | AH30: 27197650 | AI30: 3.1060746e+08 | AJ30: 5491.19 | AK30: TS I Switchyard Modi | AL30: NL-C-TS1-001 | AM30: 6* PRJ NL-C-TS1-001 TS I Switchyard Modi | AN30: 307545691 | AO30: 283409806 | AP30: 24135885 | AQ30: 7.8 | AR30: 307545691 | AS30: 257973125 | AT30: 49572566 | AU30: 16.1 | AV30: 0 | AW30: 25436681 | AX30: -25436681 | AY30: 0 | AZ30: 0 | BA30: 0 | BB30: 0 | BC30: 0 | BD30: 0 | BE30: 0 | BF30: 0 | BG30: 0 | BH30: 0 | BI30: 0 | BJ30: 0 | BK30: 0 | BL30: 307545691 | BM30: 283409806 | BN30: 24135885 | BO30: 7.8 | BP30: TS I Switchyard Modi
A31: 6* Wind Turbine Project PRJ NL-C-WND-001 | B31: 23203970 | C31: 18416660 | D31: 4604165 | E31: 23020825 | F31: 183145 | G31: 18416660 | H31: 18416660 | I31: 0 | J31: 18416660 | K31: 0 | L31: 4787310 | M31: 0 | N31: 4604165 | O31: 4604165 | P31: 183145 | Q31: 0 | R31: 0 | S31: 0 | T31: 0 | U31: 0 | V31: 0 | W31: 0 | X31: 0 | Y31: 0 | Z31: 0 | AA31: 0 | AB31: 0 | AC31: 0 | AD31: 0 | AE31: 0 | AF31: 23203970 | AG31: 18416660 | AH31: 4604165 | AI31: 23020825 | AJ31: 183145 | AK31: Wind Turbine Project | AL31: NL-C-WND-001 | AM31: 6* PRJ NL-C-WND-001 Wind Turbine Project | AN31: 0 | AO31: 18416660 | AP31: -18416660 | AQ31: 0 | AR31: 0 | AS31: 18416660 | AT31: -18416660 | AU31: 0 | AV31: 0 | AW31: 0 | AX31: 0 | AY31: 0 | AZ31: 0 | BA31: 0 | BB31: 0 | BC31: 0 | BD31: 0 | BE31: 0 | BF31: 0 | BG31: 0 | BH31: 0 | BI31: 0 | BJ31: 0 | BK31: 0 | BL31: 0 | BM31: 18416660 | BN31: -18416660 | BO31: 0 | BP31: Wind Turbine Project
... A42: 6* Safety Capital Mater PRJ NL-M-SFT-001 | B42: 8766352.1 | C42: 8766352.1 | D42: 0 | E42: 8766352.1 | F42: 0 | G42: 8766352.1 | H42: 8766352.1 | I42: 0 | J42: 8766352.1 | K42: 0 | L42: 0 | M42: 0 | N42: 0 | O42: 0 | P42: 0 | Q42: 0 | R42: 0 | S42: 0 | T42: 0 | U42: 0 | V42: 0 | W42: 0 | X42: 0 | Y42: 0 | Z42: 0 | AA42: 0 | AB42: 0 | AC42: 0 | AD42: 0 | AE42: 0 | AF42: 8766352.1 | AG42: 8766352.1 | AH42: 0 | AI42: 8766352.1 | AJ42: 0 | AK42: Safety Capital Mater | AL42: NL-M-SFT-001 | AM42: 6* PRJ NL-M-SFT-001 Safety Capital Mater | AN42: 30000000 | AO42: 8766352 | AP42: 21233648 | AQ42: 70.8 | AR42: 30000000 | AS42: 8766352 | AT42: 21233648 | AU42: 70.8 | AV42: 0 | AW42: 0 | AX42: 0 | AY42: 0 | AZ42: 0 | BA42: 0 | BB42: 0 | BC42: 0 | BD42: 0 | BE42: 0 | BF42: 0 | BG42: 0 | BH42: 0 | BI42: 0 | BJ42: 0 | BK42: 0 | BL42: 30000000 | BM42: 8766352 | BN42: 21233648 | BO42: 70.8 | BP42: Safety Capital Mater
A43: 6* TPS 1 Exp. Capital M PRJ NL-M-T1E-001 | B43: 40000000 | C43: 0 | D43: 0 | E43: 0 | F43: 40000000 | G43: 0 | H43: 0 | I43: 0 | J43: 0 | K43: 0 | L43: 40000000 | M43: 0 | N43: 0 | O43: 0 | P43: 40000000 | Q43: 0 | R43: 0 | S43: 0 | T43: 0 | U43: 0 | V43: 0 | W43: 0 | X43: 0 | Y43: 0 | Z43: 0 | AA43: 0 | AB43: 0 | AC43: 0 | AD43: 0 | AE43: 0 | AF43: 40000000 | AG43: 0 | AH43: 0 | AI43: 0 | AJ43: 40000000 | AK43: TPS 1 Exp. Capital M | AL43: NL-M-T1E-001
A44: 6* TPS2Exp - Capital Ma PRJ NL-M-T2E-001 | B44: 7.2433133e+08 | C44: 2.8340234e+08 | D44: 2.8077382e+08 | E44: 5.6417616e+08 | F44: 1.6015517e+08 | G44: 1.5388029e+08 | H44: 1.5388029e+08 | I44: 0 | J44: 1.5388029e+08 | K44: 0 | L44: 5.7045103e+08 | M44: 1.2952204e+08 | N44: 2.4132535e+08 | O44: 3.7084739e+08 | P44: 1.9960364e+08 | Q44: 0 | R44: 0 | S44: 39448472 | T44: 39448472 | U44: -39448472 | V44: 0 | W44: 0 | X44: 0 | Y44: 0 | Z44: 0 | AA44: 0 | AB44: 0 | AC44: 0 | AD44: 0 | AE44: 0 | AF44: 7.2433133e+08 | AG44: 2.8340234e+08 | AH44: 2.8077382e+08 | AI44: 5.6417616e+08 | AJ44: 1.6015517e+08 | AK44: TPS2Exp - Capital Ma | AL44: NL-M-T2E-001 | AM44: 6* PRJ NL-M-T2E-001 TPS2Exp - Capital Ma | AN44: 0 | AO44: 283402336 | AP44: -283402336 | AQ44: 0 | AR44: 0 | AS44: 153880293 | AT44: -153880293 | AU44: 0 | AV44: 0 | AW44: 129522043 | AX44: -129522043 | AY44: 0 | AZ44: 0 | BA44: 0 | BB44: 0 | BC44: 0 | BD44: 0 | BE44: 0 | BF44: 0 | BG44: 0 | BH44: 0 | BI44: 0 | BJ44: 0 | BK44: 0 | BL44: 0 | BM44: 283402336 | BN44: -283402336 | BO44: 0 | BP44: TPS2Exp - Capital Ma
AL45: NL-N-BSP-001 | AM45: 6* PRJ NL-N-BSP-001-01 Barsingsar Thermal N | AN45: 2576321000 | AO45: 415436751 | AP45: 2160884249 | AQ45: 83.9 | AR45: 1975171000 | AS45: 22957871 | AT45: 1952213129 | AU45: 98.8 | AV45: 601150000 | AW45: 392478880 | AX45: 208671120 | AY45: 34.7 | AZ45: 0 | BA45: 0 | BB45: 0 | BC45: 0 | BD45: 0 | BE45: 0 | BF45: 0 | BG45: 0 | BH45: 0 | BI45: 0 | BJ45: 0 | BK45: 0 | BL45: 2491321000 | BM45: 415436751 | BN45: 2075884249 | BO45: 83.3 | BP45: -01 Barsingsar Thermal N
A46: 6* Barsingsar Thermal N PRJ NL-N-BSP-001-01 | B46: 1.0681356e+09 | C46: 4.1543675e+08 | D46: 4.8692619e+08 | E46: 9.0236294e+08 | F46: 1.6577265e+08 | G46: 24415486 | H46: 22957871 | I46: 5091198.7 | J46: 28049070 | K46: -3633583.1 | L46: 1.0437201e+09 | M46: 3.9247888e+08 | N46: 4.1925841e+08 | O46: 8.1173729e+08 | P46: 2.3198281e+08 | Q46: 0 | R46: 0 | S46: 62576576 | T46: 62576576 | U46: -62576576 | V46: 0 | W46: 0 | X46: 0 | Y46: 0 | Z46: 0 | AA46: 0 | AB46: 0 | AC46: 0 | AD46: 0 | AE46: 0 | AF46: 1.0681356e+09 | AG46: 4.1543675e+08 | AH46: 4.8692619e+08 | AI46: 9.0236294e+08 | AJ46: 1.6577265e+08 | AK46: Barsingsar Thermal N | AL46: NL-N-BSP-001-01
A47: 6* Central Establishmen PRJ NL-N-CES-001 | B47: 3.2407823e+08 | C47: 2.0196157e+08 | D47: 14700306 | E47: 2.1666187e+08 | F47: 1.0741636e+08 | G47: 3.2407823e+08 | H47: 1.9489121e+08 | I47: 14700306 | J47: 2.0959151e+08 | K47: 1.1448672e+08 | L47: 0 | M47: 7070360.4 | N47: 0 | O47: 7070360.4 | P47: -7070360.4 | Q47: 0 | R47: 0 | S47: 0 | T47: 0 | U47: 0 | V47: 0 | W47: 0 | X47: 0 | Y47: 0 | Z47: 0 | AA47: 0 | AB47: 0 | AC47: 0 | AD47: 0 | AE47: 0 | AF47: 3.7089859e+08 | AG47: 2.0196157e+08 | AH47: 14700306 | AI47: 2.1666187e+08 | AJ47: 1.5423671e+08 | AK47: Central Establishmen | AL47: NL-N-CES-001 | AM47: 6* PRJ NL-N-CES-001 Central Establishmen | AN47: 468116057 | AO47: 201961569 | AP47: 266154488 | AQ47: 56.9 | AR47: 468116057 | AS47: 194891208 | AT47: 273224849 | AU47: 58.4 | AV47: 0 | AW47: 7070360 | AX47: -7070360 | AY47: 0 | AZ47: 0 | BA47: 0 | BB47: 0 | BC47: 0 | BD47: 0 | BE47: 0 | BF47: 0 | BG47: 0 | BH47: 0 | BI47: 0 | BJ47: 0 | BK47: 0 | BL47: 469980138 | BM47: 201961569 | BN47: 268018569 | BO47: 57 | BP47: Central Establishmen
A48: 6* Manager Corporate Of PRJ NL-N-CES-002 | B48: 1767875.5 | C48: 1713150 | D48: 53421 | E48: 1766571 | F48: 1304.51 | G48: 1767875.5 | H48: 1713150 | I48: 53421 | J48: 1766571 | K48: 1304.51 | L48: 0 | M48: 0 | N48: 0 | O48: 0 | P48: 0 | Q48: 0 | R48: 0 | S48: 0 | T48: 0 | U48: 0 | V48: 0 | W48: 0 | X48: 0 | Y48: 0 | Z48: 0 | AA48: 0 | AB48: 0 | AC48: 0 | AD48: 0 | AE48: 0 | AF48: 1767875.5 | AG48: 1713150 | AH48: 53421 | AI48: 1766571 | AJ48: 1304.51 | AK48: Manager Corporate Of | AL48: NL-N-CES-002 | AM48: 6* PRJ NL-N-CES-002 Manager Corporate Of | AN48: 21000000 | AO48: 1713150 | AP48: 19286850 | AQ48: 91.8 | AR48: 21000000 | AS48: 1713150 | AT48: 19286850 | AU48: 91.8 | AV48: 0 | AW48: 0 | AX48: 0 | AY48: 0 | AZ48: 0 | BA48: 0 | BB48: 0 | BC48: 0 | BD48: 0 | BE48: 0 | BF48: 0 | BG48: 0 | BH48: 0 | BI48: 0 | BJ48: 0 | BK48: 0 | BL48: 21000000 | BM48: 1713150 | BN48: 19286850 | BO48: 91.8 | BP48: Manager Corporate Of
A49: 6* CISF Non-Plan CapEx PRJ NL-N-CIS-001 | B49: 19625820 | C49: 1911305 | D49: 4877892 | E49: 6789197 | F49: 12836623 | G49: 1911304.9 | H49: 1911305 | I49: 0 | J49: 1911305 | K49: -0.02 | L49: 17714515 | M49: 0 | N49: 4877892 | O49: 4877892 | P49: 12836623 | Q49: 0 | R49: 0 | S49: 0 | T49: 0 | U49: 0 | V49: 0 | W49: 0 | X49: 0 | Y49: 0 | Z49: 0 | AA49: 0 | AB49: 0 | AC49: 0 | AD49: 0 | AE49: 0 | AF49: 19625820 | AG49: 1911305 | AH49: 4877892 | AI49: 6789197 | AJ49: 12836623 | AK49: CISF Non-Plan CapEx | AL49: NL-N-CIS-001 | AM49: 6* PRJ NL-N-CIS-001 CISF Non-Plan CapEx | AN49: 19113000 | AO49: 1911305 | AP49: 17201695 | AQ49: 90 | AR49: 5713000 | AS49: 1911305 | AT49: 3801695 | AU49: 66.5 | AV49: 13400000 | AW49: 0 | AX49: 13400000 | AY49: 100 | AZ49: 0 | BA49: 0 | BB49: 0 | BC49: 0 | BD49: 0 | BE49: 0 | BF49: 0 | BG49: 0 | BH49: 0 | BI49: 0 | BJ49: 0 | BK49: 0 | BL49: 19113000 | BM49: 1911305 | BN49: 17201695 | BO49: 90 | BP49: CISF Non-Plan CapEx
A50: 6* Computer Services No PRJ NL-N-COM-001 | B50: 174000000 | C50: 81631037 | D50: 71403572 | E50: 1.5303461e+08 | F50: 20965391 | G50: 42718324 | H50: 43503691 | I50: 0 | J50: 43503691 | K50: -785366.41 | L50: 1.3128168e+08 | M50: 38127347 | N50: 71403572 | O50: 1.0953092e+08 | P50: 21750757 | Q50: 0 | R50: 0 | S50: 0 | T50: 0 | U50: 0 | V50: 0 | W50: 0 | X50: 0 | Y50: 0 | Z50: 0 | AA50: 0 | AB50: 0 | AC50: 0 | AD50: 0 | AE50: 0 | AF50: 174000000 | AG50: 81631037 | AH50: 71403572 | AI50: 1.5303461e+08 | AJ50: 20965391 | AK50: Computer Services No | AL50: NL-N-COM-001 | AM50: 6* PRJ NL-N-COM-001 Computer Services No | AN50: 758067125 | AO50: 81631037 | AP50: 676436088 | AQ50: 89.2 | AR50: 497067125 | AS50: 43503691 | AT50: 453563434 | AU50: 91.2 | AV50: 261000000 | AW50: 38127347 | AX50: 222872653 | AY50: 85.4 | AZ50: 0 | BA50: 0 | BB50: 0 | BC50: 0 | BD50: 0 | BE50: 0 | BF50: 0 | BG50: 0 | BH50: 0 | BI50: 0 | BJ50: 0 | BK50: 0 | BL50: 758068010 | BM50: 81631037 | BN50: 676436973 | BO50: 89.2 | BP50: Computer Services No
A51: 6* Corporate Contracts PRJ NL-N-CON-001 | B51: 9694171.7 | C51: 8014162.7 | D51: 494418 | E51: 8508580.7 | F51: 1185590.9 | G51: 919299.96 | H51: 919299.96 | I51: 0 | J51: 919299.96 | K51: 0 | L51: 8774871.7 | M51: 7094862.8 | N51: 494418 | O51: 7589280.8 | P51: 1185590.9 | Q51: 0 | R51: 0 | S51: 0 | T51: 0 | U51: 0 | V51: 0 | W51: 0 | X51: 0 | Y51: 0 | Z51: 0 | AA51: 0 | AB51: 0 | AC51: 0 | AD51: 0 | AE51: 0 | AF51: 9694171.7 | AG51: 8014162.7 | AH51: 494418 | AI51: 8508580.7 | AJ51: 1185590.9 | AK51: Corporate Contracts | AL51: NL-N-CON-001 | AM51: 6* PRJ NL-N-CON-001 Corporate Contracts | AN51: 8645100 | AO51: 8014163 | AP51: 630937 | AQ51: 7.3 | AR51: 2285000 | AS51: 919300 | AT51: 1365700 | AU51: 59.8 | AV51: 6360100 | AW51: 7094863 | AX51: -734763 | AY51: -11.6 | AZ51: 0 | BA51: 0 | BB51: 0 | BC51: 0 | BD51: 0 | BE51: 0 | BF51: 0 | BG51: 0 | BH51: 0 | BI51: 0 | BJ51: 0 | BK51: 0 | BL51: 8645100 | BM51: 8014163 | BN51: 630937 | BO51: 7.3 | BP51: Corporate Contracts
A52: 6* CARD/ Disposal/ MM N PRJ NL-N-CRD-001 | B52: 46221858 | C52: 7647671.3 | D52: 3639627.1 | E52: 11287298 | F52: 34934560 | G52: 6050035.1 | H52: 6050035.1 | I52: 0 | J52: 6050035.1 | K52: 0 | L52: 40171823 | M52: 1597636.1 | N52: 3639627.1 | O52: 5237263.2 | P52: 34934560 | Q52: 0 | R52: 0 | S52: 0 | T52: 0 | U52: 0 | V52: 0 | W52: 0 | X52: 0 | Y52: 0 | Z52: 0 | AA52: 0 | AB52: 0 | AC52: 0 | AD52: 0 | AE52: 0 | AF52: 46221858 | AG52: 7647671.3 | AH52: 3639627.1 | AI52: 11287298 | AJ52: 34934560 | AK52: CARD/ Disposal/ MM N | AL52: NL-N-CRD-001 | AM52: 6* PRJ NL-N-CRD-001 CARD/ Disposal/ MM N | AN52: 66800000 | AO52: 7647671 | AP52: 59152329 | AQ52: 88.6 | AR52: 66800000 | AS52: 6050035 | AT52: 60749965 | AU52: 90.9 | AV52: 0 | AW52: 1597636 | AX52: -1597636 | AY52: 0 | AZ52: 0 | BA52: 0 | BB52: 0 | BC52: 0 | BD52: 0 | BE52: 0 | BF52: 0 | BG52: 0 | BH52: 0 | BI52: 0 | BJ52: 0 | BK52: 0 | BL52: 66800000 | BM52: 7647671 | BN52: 59152329 | BO52: 88.6 | BP52: CARD/ Disposal/ MM N
A53: 6* Central Workshop Non PRJ NL-N-CWS-001 | B53: 46883809 | C53: 408509.99 | D53: 27590245 | E53: 27998755 | F53: 18885054 | G53: 0 | H53: -0.01 | I53: 0 | J53: -0.01 | K53: 0.01 | L53: 46883809 | M53: 408510 | N53: 27590245 | O53: 27998755 | P53: 18885054 | Q53: 0 | R53: 0 | S53: 0 | T53: 0 | U53: 0 | V53: 0 | W53: 0 | X53: 0 | Y53: 0 | Z53: 0 | AA53: 0 | AB53: 0 | AC53: 0 | AD53: 0 | AE53: 0 | AF53: 46883809 | AG53: 408509.99 | AH53: 27590245 | AI53: 27998755 | AJ53: 18885054 | AK53: Central Workshop Non | AL53: NL-N-CWS-001 | AM53: 6* PRJ NL-N-CWS-001 Central Workshop Non | AN53: 20400000 | AO53: 408510 | AP53: 19991490 | AQ53: 98 | AR53: 1500000 | AS53: 0 | AT53: 1500000 | AU53: 100 | AV53: 18900000 | AW53: 408510 | AX53: 18491490 | AY53: 97.8 | AZ53: 0 | BA53: 0 | BB53: 0 | BC53: 0 | BD53: 0 | BE53: 0 | BF53: 0 | BG53: 0 | BH53: 0 | BI53: 0 | BJ53: 0 | BK53: 0 | BL53: 20450000 | BM53: 408510 | BN53: 20041490 | BO53: 98 | BP53: Central Workshop Non
A54: 6* Education Non-Plan C PRJ NL-N-EDU-001 | B54: 18997190 | C54: 98100.04 | D54: 5740190.2 | E54: 5838290.2 | F54: 13158900 | G54: 0 | H54: 0 | I54: 0 | J54: 0 | K54: 0 | L54: 18997190 | M54: 98100.04 | N54: 5740190.2 | O54: 5838290.2 | P54: 13158900 | Q54: 0 | R54: 0 | S54: 0 | T54: 0 | U54: 0 | V54: 0 | W54: 0 | X54: 0 | Y54: 0 | Z54: 0 | AA54: 0 | AB54: 0 | AC54: 0 | AD54: 0 | AE54: 0 | AF54: 18997190 | AG54: 98100.04 | AH54: 5740190.2 | AI54: 5838290.2 | AJ54: 13158900 | AK54: Education Non-Plan C | AL54: NL-N-EDU-001 | AM54: 6* PRJ NL-N-EDU-001 Education Non-Plan C | AN54: 14500000 | AO54: 98100 | AP54: 14401900 | AQ54: 99.3 | AR54: 0 | AS54: 0 | AT54: 0 | AU54: 0 | AV54: 14500000 | AW54: 98100 | AX54: 14401900 | AY54: 99.3 | AZ54: 0 | BA54: 0 | BB54: 0 | BC54: 0 | BD54: 0 | BE54: 0 | BF54: 0 | BG54: 0 | BH54: 0 | BI54: 0 | BJ54: 0 | BK54: 0 | BL54: 14500000 | BM54: 98100 | BN54: 14401900 | BO54: 99.3 | BP54: Education Non-Plan C
A55: 6* Electrical &Communic PRJ NL-N-ENC-001 | B55: 76083064 | C55: 45461742 | D55: 3944694.1 | E55: 49406436 | F55: 26676629 | G55: 37135315 | H55: 37135315 | I55: 1430620.9 | J55: 38565936 | K55: -1430620.9 | L55: 38947749 | M55: 8326426.5 | N55: 2514073.2 | O55: 10840500 | P55: 28107250 | Q55: 0 | R55: 0 | S55: 0 | T55: 0 | U55: 0 | V55: 0 | W55: 0 | X55: 0 | Y55: 0 | Z55: 0 | AA55: 0 | AB55: 0 | AC55: 0 | AD55: 0 | AE55: 0 | AF55: 76083064 | AG55: 45461742 | AH55: 3944694.1 | AI55: 49406436 | AJ55: 26676629 | AK55: Electrical &Communic | AL55: NL-N-ENC-001 | AM55: 6* PRJ NL-N-ENC-001 Electrical &Communic | AN55: 62955000 | AO55: 45461742 | AP55: 17493258 | AQ55: 27.8 | AR55: 62955000 | AS55: 37135315 | AT55: 25819685 | AU55: 41 | AV55: 0 | AW55: 8326426 | AX55: -8326426 | AY55: 0 | AZ55: 0 | BA55: 0 | BB55: 0 | BC55: 0 | BD55: 0 | BE55: 0 | BF55: 0 | BG55: 0 | BH55: 0 | BI55: 0 | BJ55: 0 | BK55: 0 | BL55: 62955000 | BM55: 45461742 | BN55: 17493258 | BO55: 27.8 | BP55: Electrical &Communic
A56: 6* Corporate Finance No PRJ NL-N-FIN-001 | B56: 3750000 | C56: 1662032.1 | D56: 0 | E56: 1662032.1 | F56: 2087967.9 | G56: 1339622.1 | H56: 1339622.1 | I56: 0 | J56: 1339622.1 | K56: 0 | L56: 2410377.9 | M56: 322410 | N56: 0 | O56: 322410 | P56: 2087967.9 | Q56: 0 | R56: 0 | S56: 0 | T56: 0 | U56: 0 | V56: 0 | W56: 0 | X56: 0 | Y56: 0 | Z56: 0 | AA56: 0 | AB56: 0 | AC56: 0 | AD56: 0 | AE56: 0 | AF56: 3750000 | AG56: 1662032.1 | AH56: 0 | AI56: 1662032.1 | AJ56: 2087967.9 | AK56: Corporate Finance No | AL56: NL-N-FIN-001 | AM56: 6* PRJ NL-N-FIN-001 Corporate Finance No | AN56: 1353800 | AO56: 1662032 | AP56: -308232 | AQ56: -22.8 | AR56: 1353800 | AS56: 1339622 | AT56: 14178 | AU56: 1 | AV56: 0 | AW56: 322410 | AX56: -322410 | AY56: 0 | AZ56: 0 | BA56: 0 | BB56: 0 | BC56: 0 | BD56: 0 | BE56: 0 | BF56: 0 | BG56: 0 | BH56: 0 | BI56: 0 | BJ56: 0 | BK56: 0 | BL56: 1353800 | BM56: 1662032 | BN56: -308232 | BO56: -22.8 | BP56: Corporate Finance No
A57: 6* Geology Non Plan CAP PRJ NL-N-GEO-001 | B57: 700000 | C57: 430764.01 | D57: 0 | E57: 430764.01 | F57: 269235.99 | G57: 0 | H57: 0 | I57: 0 | J57: 0 | K57: 0 | L57: 700000 | M57: 430764.01 | N57: 0 | O57: 430764.01 | P57: 269235.99 | Q57: 0 | R57: 0 | S57: 0 | T57: 0 | U57: 0 | V57: 0 | W57: 0 | X57: 0 | Y57: 0 | Z57: 0 | AA57: 0 | AB57: 0 | AC57: 0 | AD57: 0 | AE57: 0 | AF57: 700000 | AG57: 430764.01 | AH57: 0 | AI57: 430764.01 | AJ57: 269235.99 | AK57: Geology Non Plan CAP | AL57: NL-N-GEO-001 | AM57: 6* PRJ NL-N-GEO-001 Geology Non Plan CAP | AN57: 700000 | AO57: 430764 | AP57: 269236 | AQ57: 38.5 | AR57: 0 | AS57: 0 | AT57: 0 | AU57: 0 | AV57: 700000 | AW57: 430764 | AX57: 269236 | AY57: 38.5 | AZ57: 0 | BA57: 0 | BB57: 0 | BC57: 0 | BD57: 0 | BE57: 0 | BF57: 0 | BG57: 0 | BH57: 0 | BI57: 0 | BJ57: 0 | BK57: 0 | BL57: 700000 | BM57: 430764 | BN57: 269236 | BO57: 38.5 | BP57: Geology Non Plan CAP
A58: 6* GH Non Plan CAPEX 20 PRJ NL-N-GHO-001 | B58: 56335968 | C58: 41108535 | D58: 17346059 | E58: 58454593 | F58: -2118625.9 | G58: 29687989 | H58: 36593615 | I58: 0 | J58: 36593615 | K58: -6905626.5 | L58: 26647979 | M58: 4514919.6 | N58: 17346059 | O58: 21860978 | P58: 4787000.7 | Q58: 0 | R58: 0 | S58: 0 | T58: 0 | U58: 0 | V58: 0 | W58: 0 | X58: 0 | Y58: 0 | Z58: 0 | AA58: 0 | AB58: 0 | AC58: 0 | AD58: 0 | AE58: 0 | AF58: 56441593 | AG58: 41108535 | AH58: 17346059 | AI58: 58454593 | AJ58: -2013000.7 | AK58: GH Non Plan CAPEX 20 | AL58: NL-N-GHO-001 | AM58: 6* PRJ NL-N-GHO-001 GH Non Plan CAPEX 20 | AN58: 80000000 | AO58: 41108535 | AP58: 38891465 | AQ58: 48.6 | AR58: 80000000 | AS58: 36593615 | AT58: 43406385 | AU58: 54.3 | AV58: 0 | AW58: 4514920 | AX58: -4514920 | AY58: 0 | AZ58: 0 | BA58: 0 | BB58: 0 | BC58: 0 | BD58: 0 | BE58: 0 | BF58: 0 | BG58: 0 | BH58: 0 | BI58: 0 | BJ58: 0 | BK58: 0 | BL58: 80000000 | BM58: 41108535 | BN58: 38891465 | BO58: 48.6 | BP58: GH Non Plan CAPEX 20
A59: 6* GH Non Plan Capex 20 PRJ NL-N-GHO-002 | B59: 48100000 | C59: 0 | D59: 2181356 | E59: 2181356 | F59: 45918644 | G59: 0 | H59: 0 | I59: 0 | J59: 0 | K59: 0 | L59: 48100000 | M59: 0 | N59: 2181356 | O59: 2181356 | P59: 45918644 | Q59: 0 | R59: 0 | S59: 0 | T59: 0 | U59: 0 | V59: 0 | W59: 0 | X59: 0 | Y59: 0 | Z59: 0 | AA59: 0 | AB59: 0 | AC59: 0 | AD59: 0 | AE59: 0 | AF59: 48100000 | AG59: 0 | AH59: 2181356 | AI59: 2181356 | AJ59: 45918644 | AK59: GH Non Plan Capex 20 | AL59: NL-N-GHO-002
A60: 6* IE Wing Non Plan Cap PRJ NL-N-IEC-001 | B60: 300000 | C60: 14848.95 | D60: 0 | E60: 14848.95 | F60: 285151.05 | G60: 0 | H60: 0 | I60: 0 | J60: 0 | K60: 0 | L60: 300000 | M60: 14848.95 | N60: 0 | O60: 14848.95 | P60: 285151.05 | Q60: 0 | R60: 0 | S60: 0 | T60: 0 | U60: 0 | V60: 0 | W60: 0 | X60: 0 | Y60: 0 | Z60: 0 | AA60: 0 | AB60: 0 | AC60: 0 | AD60: 0 | AE60: 0 | AF60: 300000 | AG60: 14848.95 | AH60: 0 | AI60: 14848.95 | AJ60: 285151.05 | AK60: IE Wing Non Plan Cap | AL60: NL-N-IEC-001 | AM60: 6* PRJ NL-N-IEC-001 IE Wing Non Plan Cap | AN60: 20500000 | AO60: 14849 | AP60: 20485151 | AQ60: 99.9 | AR60: 20500000 | AS60: 0 | AT60: 20500000 | AU60: 100 | AV60: 0 | AW60: 14849 | AX60: -14849 | AY60: 0 | AZ60: 0 | BA60: 0 | BB60: 0 | BC60: 0 | BD60: 0 | BE60: 0 | BF60: 0 | BG60: 0 | BH60: 0 | BI60: 0 | BJ60: 0 | BK60: 0 | BL60: 20500000 | BM60: 14849 | BN60: 20485151 | BO60: 99.9 | BP60: IE Wing Non Plan Cap
A61: 6* Land Acquisition Non PRJ NL-N-LAQ-001 | B61: 7.7505924e+08 | C61: 6.5092671e+08 | D61: 1.1678426e+08 | E61: 7.6771097e+08 | F61: 7348274.9 | G61: 6.1390703e+08 | H61: 6.1390703e+08 | I61: 676826.98 | J61: 6.1458386e+08 | K61: -676826.98 | L61: 1.6115221e+08 | M61: 37019679 | N61: 1.1610743e+08 | O61: 1.5312711e+08 | P61: 8025101.9 | Q61: 0 | R61: 0 | S61: 0 | T61: 0 | U61: 0 | V61: 0 | W61: 0 | X61: 0 | Y61: 0 | Z61: 0 | AA61: 0 | AB61: 0 | AC61: 0 | AD61: 0 | AE61: 0 | AF61: 7.7505924e+08 | AG61: 6.5092671e+08 | AH61: 1.1678426e+08 | AI61: 7.6771097e+08 | AJ61: 7348274.9 | AK61: Land Acquisition Non | AL61: NL-N-LAQ-001 | AM61: 6* PRJ NL-N-LAQ-001 Land Acquisition Non | AN61: 873800000 | AO61: 650926712 | AP61: 222873288 | AQ61: 25.5 | AR61: 848800000 | AS61: 613907034 | AT61: 234892966 | AU61: 27.7 | AV61: 25000000 | AW61: 37019679 | AX61: -12019679 | AY61: -48.1 | AZ61: 0 | BA61: 0 | BB61: 0 | BC61: 0 | BD61: 0 | BE61: 0 | BF61: 0 | BG61: 0 | BH61: 0 | BI61: 0 | BJ61: 0 | BK61: 0 | BL61: 432800000 | BM61: 650926712 | BN61: -218126712 | BO61: -50.4 | BP61: Land Acquisition Non
A62: 6* Learning and Develop PRJ NL-N-LDC-001 | B62: 57884278 | C62: 23836007 | D62: 15801981 | E62: 39637988 | F62: 18246290 | G62: 3791378 | H62: 4552580 | I62: 0 | J62: 4552580 | K62: -761202.07 | L62: 54092900 | M62: 19283427 | N62: 15801981 | O62: 35085408 | P62: 19007492 | Q62: 0 | R62: 0 | S62: 0 | T62: 0 | U62: 0 | V62: 0 | W62: 0 | X62: 0 | Y62: 0 | Z62: 0 | AA62: 0 | AB62: 0 | AC62: 0 | AD62: 0 | AE62: 0 | AF62: 57884278 | AG62: 23836007 | AH62: 15801981 | AI62: 39637988 | AJ62: 18246290 | AK62: Learning and Develop | AL62: NL-N-LDC-001 | AM62: 6* PRJ NL-N-LDC-001 Learning and Develop | AN62: 104465000 | AO62: 23836007 | AP62: 80628993 | AQ62: 77.2 | AR62: 65200000 | AS62: 4552580 | AT62: 60647420 | AU62: 93 | AV62: 39265000 | AW62: 19283427 | AX62: 19981573 | AY62: 50.9 | AZ62: 0 | BA62: 0 | BB62: 0 | BC62: 0 | BD62: 0 | BE62: 0 | BF62: 0 | BG62: 0 | BH62: 0 | BI62: 0 | BJ62: 0 | BK62: 0 | BL62: 104465000 | BM62: 23836007 | BN62: 80628993 | BO62: 77.2 | BP62: Learning and Develop
A63: 6* MINE- IA Non Plan CA PRJ NL-N-M1A-001 | B63: 2.6521674e+09 | C63: 3.4392886e+08 | D63: 1.7216071e+09 | E63: 2.0655826e+09 | F63: 5.8658474e+08 | G63: 1.3269324e+08 | H63: 1.3212309e+08 | I63: 0 | J63: 1.3216979e+08 | K63: 523442.38 | L63: 2.5194741e+09 | M63: 2.1180577e+08 | N63: 1.6185505e+09 | O63: 1.8303563e+09 | P63: 6.8911785e+08 | Q63: 0 | R63: 0 | S63: 1.0305656e+08 | T63: 1.0305656e+08 | U63: -1.0305656e+08 | V63: 0 | W63: 0 | X63: 0 | Y63: 0 | Z63: 0 | AA63: 0 | AB63: 0 | AC63: 0 | AD63: 0 | AE63: 0 | AF63: 2.6521674e+09 | AG63: 3.4392886e+08 | AH63: 1.7216071e+09 | AI63: 2.0655826e+09 | AJ63: 5.8658474e+08 | AK63: MINE- IA Non Plan CA | AL63: NL-N-M1A-001 | AM63: 6* PRJ NL-N-M1A-001 MINE- IA Non Plan CA | AN63: 1613800465 | AO63: 343928856 | AP63: 1269871610 | AQ63: 78.7 | AR63: 155 | AS63: 132123090 | AT63: -132122935 | AU63: -85163681 | AV63: 1613800310 | AW63: 211805765 | AX63: 1401994545 | AY63: 86.9 | AZ63: 0 | BA63: 0 | BB63: 0 | BC63: 0 | BD63: 0 | BE63: 0 | BF63: 0 | BG63: 0 | BH63: 0 | BI63: 0 | BJ63: 0 | BK63: 0 | BL63: 155 | BM63: 343928856 | BN63: -343928701 | BO63: -2.2168925e+08 | BP63: MINE- IA Non Plan CA
A64: 6* Barsingsar- Mines No PRJ NL-N-MBR-001 | B64: 46968520 | C64: 15199293 | D64: 24145674 | E64: 39344967 | F64: 7623553.6 | G64: 7848028.3 | H64: 7848028.3 | I64: 0 | J64: 7848028.3 | K64: 0 | L64: 39120492 | M64: 7351264.8 | N64: 24145674 | O64: 31496938 | P64: 7623553.6 | Q64: 0 | R64: 0 | S64: 0 | T64: 0 | U64: 0 | V64: 0 | W64: 0 | X64: 0 | Y64: 0 | Z64: 0 | AA64: 0 | AB64: 0 | AC64: 0 | AD64: 0 | AE64: 0 | AF64: 46968520 | AG64: 15199293 | AH64: 24145674 | AI64: 39344967 | AJ64: 7623553.6 | AK64: Barsingsar- Mines No | AL64: NL-N-MBR-001 | AM64: 6* PRJ NL-N-MBR-001 Barsingsar- Mines No | AN64: 49830000 | AO64: 15199293 | AP64: 34630707 | AQ64: 69.5 | AR64: 43330000 | AS64: 7848028 | AT64: 35481972 | AU64: 81.9 | AV64: 6500000 | AW64: 7351265 | AX64: -851265 | AY64: -13.1 | AZ64: 0 | BA64: 0 | BB64: 0 | BC64: 0 | BD64: 0 | BE64: 0 | BF64: 0 | BG64: 0 | BH64: 0 | BI64: 0 | BJ64: 0 | BK64: 0 | BL64: 49830000 | BM64: 15199293 | BN64: 34630707 | BO64: 69.5 | BP64: Barsingsar- Mines No
A65: 6* MCO Non-Plan CapEx PRJ NL-N-MCO-001 | B65: 20488339 | C65: 12942989 | D65: 1362466 | E65: 14305455 | F65: 6182884.2 | G65: 6417722.9 | H65: 6417722.9 | I65: 0 | J65: 6417722.9 | K65: 0 | L65: 14070616 | M65: 6525265.8 | N65: 1362466 | O65: 7887731.8 | P65: 6182884.2 | Q65: 0 | R65: 0 | S65: 0 | T65: 0 | U65: 0 | V65: 0 | W65: 0 | X65: 0 | Y65: 0 | Z65: 0 | AA65: 0 | AB65: 0 | AC65: 0 | AD65: 0 | AE65: 0 | AF65: 20488339 | AG65: 12942989 | AH65: 1362466 | AI65: 14305455 | AJ65: 6182884.2 | AK65: MCO Non-Plan CapEx | AL65: NL-N-MCO-001 | AM65: 6* PRJ NL-N-MCO-001 MCO Non-Plan CapEx | AN65: 127500000 | AO65: 12942989 | AP65: 114557011 | AQ65: 89.8 | AR65: 98800000 | AS65: 6417723 | AT65: 92382277 | AU65: 93.5 | AV65: 28700000 | AW65: 6525266 | AX65: 22174734 | AY65: 77.3 | AZ65: 0 | BA65: 0 | BB65: 0 | BC65: 0 | BD65: 0 | BE65: 0 | BF65: 0 | BG65: 0 | BH65: 0 | BI65: 0 | BJ65: 0 | BK65: 0 | BL65: 127500000 | BM65: 12942989 | BN65: 114557011 | BO65: 89.8 | BP65: MCO Non-Plan CapEx
A66: 6* Mechanical Services PRJ NL-N-MES-001 | B66: 5.4143794e+09 | C66: 3.5355036e+09 | D66: 1.4945473e+09 | E66: 5.0300509e+09 | F66: 3.8432853e+08 | G66: 2.6398893e+09 | H66: 2.6398893e+09 | I66: 0 | J66: 2.6398893e+09 | K66: -0.03 | L66: 2.7744901e+09 | M66: 8.9561428e+08 | N66: 6.7213072e+08 | O66: 1.567745e+09 | P66: 1.2067451e+09 | Q66: 0 | R66: 0 | S66: 8.224166e+08 | T66: 8.224166e+08 | U66: -8.224166e+08 | V66: 0 | W66: 0 | X66: 0 | Y66: 0 | Z66: 0 | AA66: 0 | AB66: 0 | AC66: 0 | AD66: 0 | AE66: 0 | AF66: 5.4143794e+09 | AG66: 3.5355036e+09 | AH66: 1.4945473e+09 | AI66: 5.0300509e+09 | AJ66: 3.8432853e+08 | AK66: Mechanical Services | AL66: NL-N-MES-001 | AM66: 6* PRJ NL-N-MES-001 Mechanical Services | AN66: 5755800000 | AO66: 3535503571 | AP66: 2220296429 | AQ66: 38.6 | AR66: 3449800000 | AS66: 2639889286 | AT66: 809910714 | AU66: 23.5 | AV66: 2306000000 | AW66: 895614285 | AX66: 1410385715 | AY66: 61.2 | AZ66: 0 | BA66: 0 | BB66: 0 | BC66: 0 | BD66: 0 | BE66: 0 | BF66: 0 | BG66: 0 | BH66: 0 | BI66: 0 | BJ66: 0 | BK66: 0 | BL66: 5755853475 | BM66: 3535503571 | BN66: 2220349904 | BO66: 38.6 | BP66: Mechanical Services
A67: 6* Management Services PRJ NL-N-MIS-001 | B67: 0 | C67: 0 | D67: 0 | E67: 0 | F67: 0 | G67: 0 | H67: 0 | I67: 0 | J67: 0 | K67: 0 | L67: 0 | M67: 0 | N67: 0 | O67: 0 | P67: 0 | Q67: 0 | R67: 0 | S67: 0 | T67: 0 | U67: 0 | V67: 0 | W67: 0 | X67: 0 | Y67: 0 | Z67: 0 | AA67: 0 | AB67: 0 | AC67: 0 | AD67: 0 | AE67: 0 | AF67: 0 | AG67: 0 | AH67: 0 | AI67: 0 | AJ67: 0 | AK67: Management Services | AL67: NL-N-MIS-001 | AM67: 6* PRJ NL-N-MIS-001 Management Services | AN67: 100000 | AO67: 0 | AP67: 100000 | AQ67: 100 | AR67: 100000 | AS67: 0 | AT67: 100000 | AU67: 100 | AV67: 0 | AW67: 0 | AX67: 0 | AY67: 0 | AZ67: 0 | BA67: 0 | BB67: 0 | BC67: 0 | BD67: 0 | BE67: 0 | BF67: 0 | BG67: 0 | BH67: 0 | BI67: 0 | BJ67: 0 | BK67: 0 | BL67: 100000 | BM67: 0 | BN67: 100000 | BO67: 100 | BP67: Management Services
A68: 6* MMC Non-Plan CAPEX 2 PRJ NL-N-MMC-001 | B68: 60215055 | C68: 19979086 | D68: 15408720 | E68: 35387805 | F68: 24827249 | G68: 17446753 | H68: 17446753 | I68: 0 | J68: 17446753 | K68: 0.08 | L68: 42768302 | M68: 2532332.9 | N68: 13933720 | O68: 16466053 | P68: 26302249 | Q68: 0 | R68: 0 | S68: 1475000 | T68: 1475000 | U68: -1475000 | V68: 0 | W68: 0 | X68: 0 | Y68: 0 | Z68: 0 | AA68: 0 | AB68: 0 | AC68: 0 | AD68: 0 | AE68: 0 | AF68: 60215055 | AG68: 19979086 | AH68: 15408720 | AI68: 35387805 | AJ68: 24827249 | AK68: MMC Non-Plan CAPEX 2 | AL68: NL-N-MMC-001 | AM68: 6* PRJ NL-N-MMC-001 MMC Non-Plan CAPEX 2 | AN68: 40645000 | AO68: 19979086 | AP68: 20665914 | AQ68: 50.8 | AR68: 40645000 | AS68: 17446753 | AT68: 23198247 | AU68: 57.1 | AV68: 0 | AW68: 2532333 | AX68: -2532333 | AY68: 0 | AZ68: 0 | BA68: 0 | BB68: 0 | BC68: 0 | BD68: 0 | BE68: 0 | BF68: 0 | BG68: 0 | BH68: 0 | BI68: 0 | BJ68: 0 | BK68: 0 | BL68: 40645000 | BM68: 19979086 | BN68: 20665914 | BO68: 50.8 | BP68: MMC Non-Plan CAPEX 2
A69: 6* MINE- I Non Plan CAP PRJ NL-N-MN1-001 | B69: 2.6351563e+09 | C69: 4.933918e+08 | D69: 1.3263085e+09 | E69: 1.8206095e+09 | F69: 8.1454686e+08 | G69: 1.8125099e+08 | H69: 1.8125099e+08 | I69: 12903018 | J69: 1.9415401e+08 | K69: -12903018 | L69: 2.4539053e+09 | M69: 3.1214081e+08 | N69: 1.2266453e+09 | O69: 1.5396953e+09 | P69: 9.1421003e+08 | Q69: 0 | R69: 0 | S69: 86760147 | T69: 86760147 | U69: -86760147 | V69: 0 | W69: 0 | X69: 0 | Y69: 0 | Z69: 0 | AA69: 0 | AB69: 0 | AC69: 0 | AD69: 0 | AE69: 0 | AF69: 2.6384517e+09 | AG69: 4.933918e+08 | AH69: 1.3263085e+09 | AI69: 1.8206095e+09 | AJ69: 8.1784221e+08 | AK69: MINE- I Non Plan CAP | AL69: NL-N-MN1-001 | AM69: 6* PRJ NL-N-MN1-001 MINE- I Non Plan CAP | AN69: 4263500000 | AO69: 493391805 | AP69: 3770108195 | AQ69: 88.4 | AR69: 2119600000 | AS69: 181250994 | AT69: 1938349006 | AU69: 91.4 | AV69: 2143900000 | AW69: 312140811 | AX69: 1831759189 | AY69: 85.4 | AZ69: 0 | BA69: 0 | BB69: 0 | BC69: 0 | BD69: 0 | BE69: 0 | BF69: 0 | BG69: 0 | BH69: 0 | BI69: 0 | BJ69: 0 | BK69: 0 | BL69: 4263500000 | BM69: 493391805 | BN69: 3770108195 | BO69: 88.4 | BP69: MINE- I Non Plan CAP
A70: 6* MINE- II Non Plan CA PRJ NL-N-MN2-001 | B70: 3.4369307e+09 | C70: 1.1919115e+09 | D70: 1.4996022e+09 | E70: 2.6915137e+09 | F70: 7.4541693e+08 | G70: 3.1614931e+08 | H70: 3.1614931e+08 | I70: 76493161 | J70: 3.9264247e+08 | K70: -76493161 | L70: 3.1207813e+09 | M70: 8.7576221e+08 | N70: 1.3069886e+09 | O70: 2.1827508e+09 | P70: 9.3803054e+08 | Q70: 0 | R70: 0 | S70: 1.1612045e+08 | T70: 1.1612045e+08 | U70: -1.1612045e+08 | V70: 0 | W70: 0 | X70: 0 | Y70: 0 | Z70: 0 | AA70: 0 | AB70: 0 | AC70: 0 | AD70: 0 | AE70: 0 | AF70: 3.4369307e+09 | AG70: 1.1919115e+09 | AH70: 1.4996022e+09 | AI70: 2.6915137e+09 | AJ70: 7.4541693e+08 | AK70: MINE- II Non Plan CA | AL70: NL-N-MN2-001 | AM70: 6* PRJ NL-N-MN2-001 MINE- II Non Plan CA | AN70: 4198700000 | AO70: 1191911518 | AP70: 3006788482 | AQ70: 71.6 | AR70: 1731000000 | AS70: 316149312 | AT70: 1414850688 | AU70: 81.7 | AV70: 2467700000 | AW70: 875762207 | AX70: 1591937793 | AY70: 64.5 | AZ70: 0 | BA70: 0 | BB70: 0 | BC70: 0 | BD70: 0 | BE70: 0 | BF70: 0 | BG70: 0 | BH70: 0 | BI70: 0 | BJ70: 0 | BK70: 0 | BL70: 4198700000 | BM70: 1191911518 | BN70: 3006788482 | BO70: 71.6 | BP70: MINE- II Non Plan CA
A71: 6* NNTPP Non Plan CAPEX PRJ NL-N-NNT-001 | B71: 1.9459586e+09 | C71: 8.1829157e+08 | D71: 6.8918451e+08 | E71: 1.5074761e+09 | F71: 4.3848247e+08 | G71: 5.8507021e+08 | H71: 5.8507021e+08 | I71: 582951.94 | J71: 5.8565316e+08 | K71: -582951.9 | L71: 1.3608883e+09 | M71: 2.3322136e+08 | N71: 6.0085961e+08 | O71: 8.3408097e+08 | P71: 5.2680737e+08 | Q71: 0 | R71: 0 | S71: 87741956 | T71: 87741956 | U71: -87741956 | V71: 0 | W71: 0 | X71: 0 | Y71: 0 | Z71: 0 | AA71: 0 | AB71: 0 | AC71: 0 | AD71: 0 | AE71: 0 | AF71: 1.9459586e+09 | AG71: 8.1829157e+08 | AH71: 6.8918451e+08 | AI71: 1.5074761e+09 | AJ71: 4.3848247e+08 | AK71: NNTPP Non Plan CAPEX | AL71: NL-N-NNT-001 | AM71: 6* PRJ NL-N-NNT-001 NNTPP Non Plan CAPEX | AN71: 437100000 | AO71: 818291571 | AP71: -381191571 | AQ71: -87.2 | AR71: 0 | AS71: 585070207 | AT71: -585070207 | AU71: 0 | AV71: 437100000 | AW71: 233221364 | AX71: 203878636 | AY71: 46.6 | AZ71: 0 | BA71: 0 | BB71: 0 | BC71: 0 | BD71: 0 | BE71: 0 | BF71: 0 | BG71: 0 | BH71: 0 | BI71: 0 | BJ71: 0 | BK71: 0 | BL71: 437100000 | BM71: 818291571 | BN71: -381191571 | BO71: -87.2 | BP71: NNTPP Non Plan CAPEX
... A78: 6* RMO Chennai Non Plan PRJ NL-N-ROC-001 | B78: 1.064849e+08 | C78: 19073243 | D78: 37261115 | E78: 56334357 | F78: 50150544 | G78: 4753313.8 | H78: 3777869.3 | I78: 0 | J78: 3777869.3 | K78: 975444.49 | L78: 1.0173159e+08 | M78: 15295373 | N78: 37261115 | O78: 52556488 | P78: 49175100 | Q78: 0 | R78: 0 | S78: 0 | T78: 0 | U78: 0 | V78: 0 | W78: 0 | X78: 0 | Y78: 0 | Z78: 0 | AA78: 0 | AB78: 0 | AC78: 0 | AD78: 0 | AE78: 0 | AF78: 1.064849e+08 | AG78: 19073243 | AH78: 37261115 | AI78: 56334357 | AJ78: 50150544 | AK78: RMO Chennai Non Plan | AL78: NL-N-ROC-001 | AM78: 6* PRJ NL-N-ROC-001 RMO Chennai Non Plan | AN78: 187600000 | AO78: 19073243 | AP78: 168526757 | AQ78: 89.8 | AR78: 187600000 | AS78: 3777869 | AT78: 183822131 | AU78: 98 | AV78: 0 | AW78: 15295373 | AX78: -15295373 | AY78: 0 | AZ78: 0 | BA78: 0 | BB78: 0 | BC78: 0 | BD78: 0 | BE78: 0 | BF78: 0 | BG78: 0 | BH78: 0 | BI78: 0 | BJ78: 0 | BK78: 0 | BL78: 82800000 | BM78: 19073243 | BN78: 63726757 | BO78: 77 | BP78: RMO Chennai Non Plan
A79: 6* Security and Fire No PRJ NL-N-SEC-001 | B79: 2200000 | C79: 0 | D79: 0 | E79: 0 | F79: 2200000 | G79: 2200000 | H79: 0 | I79: 0 | J79: 0 | K79: 2200000 | L79: 0 | M79: 0 | N79: 0 | O79: 0 | P79: 0 | Q79: 0 | R79: 0 | S79: 0 | T79: 0 | U79: 0 | V79: 0 | W79: 0 | X79: 0 | Y79: 0 | Z79: 0 | AA79: 0 | AB79: 0 | AC79: 0 | AD79: 0 | AE79: 0 | AF79: 2200000 | AG79: 0 | AH79: 0 | AI79: 0 | AJ79: 2200000 | AK79: Security and Fire No | AL79: NL-N-SEC-001
A80: 6* Safety Non Plan CAPE PRJ NL-N-SFT-001 | B80: 70190919 | C80: 3267065 | D80: 11595603 | E80: 14862668 | F80: 55328251 | G80: 2005457.9 | H80: 2005457.9 | I80: 0 | J80: 2005457.9 | K80: 0 | L80: 68185461 | M80: 1261607.1 | N80: 9746853.3 | O80: 11008460 | P80: 57177001 | Q80: 0 | R80: 0 | S80: 1848750 | T80: 1848750 | U80: -1848750 | V80: 0 | W80: 0 | X80: 0 | Y80: 0 | Z80: 0 | AA80: 0 | AB80: 0 | AC80: 0 | AD80: 0 | AE80: 0 | AF80: 70190919 | AG80: 3267065 | AH80: 11595603 | AI80: 14862668 | AJ80: 55328251 | AK80: Safety Non Plan CAPE | AL80: NL-N-SFT-001 | AM80: 6* PRJ NL-N-SFT-001 Safety Non Plan CAPE | AN80: 129821000 | AO80: 3267065 | AP80: 126553935 | AQ80: 97.5 | AR80: 74826000 | AS80: 2005458 | AT80: 72820542 | AU80: 97.3 | AV80: 54995000 | AW80: 1261607 | AX80: 53733393 | AY80: 97.7 | AZ80: 0 | BA80: 0 | BB80: 0 | BC80: 0 | BD80: 0 | BE80: 0 | BF80: 0 | BG80: 0 | BH80: 0 | BI80: 0 | BJ80: 0 | BK80: 0 | BL80: 129821000 | BM80: 3267065 | BN80: 126553935 | BO80: 97.5 | BP80: Safety Non Plan CAPE
A81: 6* 10MW Solar Power Pla PRJ NL-N-SOL-001 | B81: 9000000 | C81: 0 | D81: 1125600 | E81: 1125600 | F81: 7874400 | G81: 0 | H81: 0 | I81: 0 | J81: 0 | K81: 0 | L81: 9000000 | M81: 0 | N81: 1125600 | O81: 1125600 | P81: 7874400 | Q81: 0 | R81: 0 | S81: 0 | T81: 0 | U81: 0 | V81: 0 | W81: 0 | X81: 0 | Y81: 0 | Z81: 0 | AA81: 0 | AB81: 0 | AC81: 0 | AD81: 0 | AE81: 0 | AF81: 9000000 | AG81: 0 | AH81: 1125600 | AI81: 1125600 | AJ81: 7874400 | AK81: 10MW Solar Power Pla | AL81: NL-N-SOL-001 | AM81: 6* PRJ NL-N-SOL-001 10MW Solar Power Pla | AN81: 0 | AO81: 0 | AP81: 0 | AQ81: 0 | AR81: 0 | AS81: 0 | AT81: 0 | AU81: 0 | AV81: 0 | AW81: 0 | AX81: 0 | AY81: 0 | AZ81: 0 | BA81: 0 | BB81: 0 | BC81: 0 | BD81: 0 | BE81: 0 | BF81: 0 | BG81: 0 | BH81: 0 | BI81: 0 | BJ81: 0 | BK81: 0 | BL81: 9000000 | BM81: 0 | BN81: 9000000 | BO81: 100 | BP81: 10MW Solar Power Pla
A82: 6* TPS-I Exp Non Plan C PRJ NL-N-T1E-001 | B82: 1.3375493e+09 | C82: 4.7795894e+08 | D82: 7.4698069e+08 | E82: 1.2249396e+09 | F82: 1.1260963e+08 | G82: 1.6811182e+08 | H82: 1.6811182e+08 | I82: 1980984 | J82: 1.700928e+08 | K82: -1980984 | L82: 1.1694374e+09 | M82: 3.0984712e+08 | N82: 6.9937381e+08 | O82: 1.0092209e+09 | P82: 1.6021651e+08 | Q82: 0 | R82: 0 | S82: 45625894 | T82: 45625894 | U82: -45625894 | V82: 0 | W82: 0 | X82: 0 | Y82: 0 | Z82: 0 | AA82: 0 | AB82: 0 | AC82: 0 | AD82: 0 | AE82: 0 | AF82: 1.3375493e+09 | AG82: 4.7795894e+08 | AH82: 7.4698069e+08 | AI82: 1.2249396e+09 | AJ82: 1.1260963e+08 | AK82: TPS-I Exp Non Plan C | AL82: NL-N-T1E-001 | AM82: 6* PRJ NL-N-T1E-001 TPS-I Exp Non Plan C | AN82: 2722040616 | AO82: 477958937 | AP82: 2244081679 | AQ82: 82.4 | AR82: 1701390616 | AS82: 168111818 | AT82: 1533278798 | AU82: 90.1 | AV82: 1020650000 | AW82: 309847118 | AX82: 710802882 | AY82: 69.6 | AZ82: 0 | BA82: 0 | BB82: 0 | BC82: 0 | BD82: 0 | BE82: 0 | BF82: 0 | BG82: 0 | BH82: 0 | BI82: 0 | BJ82: 0 | BK82: 0 | BL82: 2011390616 | BM82: 477958937 | BN82: 1533431679 | BO82: 76.2 | BP82: TPS-I Exp Non Plan C
A83: 6* TPS2Exp - Non Plan C PRJ NL-N-T2E-001 | B83: 6.1811479e+08 | C83: 3.0255096e+08 | D83: 1.1531126e+08 | E83: 4.1786222e+08 | F83: 2.0025257e+08 | G83: 1.6856564e+08 | H83: 1.6856552e+08 | I83: 0 | J83: 1.6856552e+08 | K83: 120.52 | L83: 4.4954915e+08 | M83: 1.3398544e+08 | N83: 95790368 | O83: 2.2977581e+08 | P83: 2.1977334e+08 | Q83: 0 | R83: 0 | S83: 19520889 | T83: 19520889 | U83: -19520889 | V83: 0 | W83: 0 | X83: 0 | Y83: 0 | Z83: 0 | AA83: 0 | AB83: 0 | AC83: 0 | AD83: 0 | AE83: 0 | AF83: 6.1811479e+08 | AG83: 3.0255096e+08 | AH83: 1.1531126e+08 | AI83: 4.1786222e+08 | AJ83: 2.0025257e+08 | AK83: TPS2Exp - Non Plan C | AL83: NL-N-T2E-001 | AM83: 6* PRJ NL-N-T2E-001 TPS2Exp - Non Plan C | AN83: 681116786 | AO83: 302550961 | AP83: 378565825 | AQ83: 55.6 | AR83: 681116786 | AS83: 168565519 | AT83: 512551267 | AU83: 75.3 | AV83: 0 | AW83: 133985441 | AX83: -133985441 | AY83: 0 | AZ83: 0 | BA83: 0 | BB83: 0 | BC83: 0 | BD83: 0 | BE83: 0 | BF83: 0 | BG83: 0 | BH83: 0 | BI83: 0 | BJ83: 0 | BK83: 0 | BL83: 681116786 | BM83: 302550961 | BN83: 378565825 | BO83: 55.6 | BP83: TPS2Exp - Non Plan C
A84: 6* TA Non Plan CAPEX PRJ NL-N-TAA-001 | B84: 1.3329817e+08 | C84: 44533238 | D84: 5569891.3 | E84: 50103129 | F84: 83195045 | G84: 44832805 | H84: 44533238 | I84: 0 | J84: 44533238 | K84: 299567.81 | L84: 88465368 | M84: 0 | N84: 5569891.3 | O84: 5569891.3 | P84: 82895477 | Q84: 0 | R84: 0 | S84: 0 | T84: 0 | U84: 0 | V84: 0 | W84: 0 | X84: 0 | Y84: 0 | Z84: 0 | AA84: 0 | AB84: 0 | AC84: 0 | AD84: 0 | AE84: 0 | AF84: 1.3329817e+08 | AG84: 44533238 | AH84: 5569891.3 | AI84: 50103129 | AJ84: 83195045 | AK84: TA Non Plan CAPEX | AL84: NL-N-TAA-001 | AM84: 6* PRJ NL-N-TAA-001 TA Non Plan CAPEX | AN84: 180527000 | AO84: 44533238 | AP84: 135993762 | AQ84: 75.3 | AR84: 180527000 | AS84: 44533238 | AT84: 135993762 | AU84: 75.3 | AV84: 0 | AW84: 0 | AX84: 0 | AY84: 0 | AZ84: 0 | BA84: 0 | BB84: 0 | BC84: 0 | BD84: 0 | BE84: 0 | BF84: 0 | BG84: 0 | BH84: 0 | BI84: 0 | BJ84: 0 | BK84: 0 | BL84: 176227000 | BM84: 44533238 | BN84: 131693762 | BO84: 74.7 | BP84: TA Non Plan CAPEX
A85: 6* TA Non-Plan CapEx Op PRJ NL-N-TAA-002 | B85: 10493522 | C85: 10493522 | D85: 0 | E85: 10493522 | F85: 0 | G85: 10493522 | H85: 10493522 | I85: 0 | J85: 10493522 | K85: 0 | L85: 0 | M85: 0 | N85: 0 | O85: 0 | P85: 0 | Q85: 0 | R85: 0 | S85: 0 | T85: 0 | U85: 0 | V85: 0 | W85: 0 | X85: 0 | Y85: 0 | Z85: 0 | AA85: 0 | AB85: 0 | AC85: 0 | AD85: 0 | AE85: 0 | AF85: 10493522 | AG85: 10493522 | AH85: 0 | AI85: 10493522 | AJ85: 0 | AK85: TA Non-Plan CapEx Op | AL85: NL-N-TAA-002 | AM85: 6* PRJ NL-N-TAA-002 TA Non-Plan CapEx Op | AN85: 0 | AO85: 10493523 | AP85: -10493523 | AQ85: 0 | AR85: 0 | AS85: 10493523 | AT85: -10493523 | AU85: 0 | AV85: 0 | AW85: 0 | AX85: 0 | AY85: 0 | AZ85: 0 | BA85: 0 | BB85: 0 | BC85: 0 | BD85: 0 | BE85: 0 | BF85: 0 | BG85: 0 | BH85: 0 | BI85: 0 | BJ85: 0 | BK85: 0 | BL85: 6786213 | BM85: 10493523 | BN85: -3707310 | BO85: -54.6 | BP85: TA Non-Plan CapEx Op
A86: 6* TA Non-Plan Capital PRJ NL-N-TAA-003 | B86: 8.8670272e+08 | C86: 1.30714e+08 | D86: 3.2283553e+08 | E86: 4.5354954e+08 | F86: 4.3315319e+08 | G86: 43625666 | H86: 43625666 | I86: 27066537 | J86: 70692204 | K86: -27066537 | L86: 8.4307706e+08 | M86: 87088338 | N86: 2.95769e+08 | O86: 3.8285733e+08 | P86: 4.6021972e+08 | Q86: 0 | R86: 0 | S86: 0 | T86: 0 | U86: 0 | V86: 0 | W86: 0 | X86: 0 | Y86: 0 | Z86: 0 | AA86: 0 | AB86: 0 | AC86: 0 | AD86: 0 | AE86: 0 | AF86: 8.8670272e+08 | AG86: 1.30714e+08 | AH86: 3.2283553e+08 | AI86: 4.5354954e+08 | AJ86: 4.3315319e+08 | AK86: TA Non-Plan Capital | AL86: NL-N-TAA-003 | AM86: 6* PRJ NL-N-TAA-003 TA Non-Plan Capital | AN86: 443062000 | AO86: 130714004 | AP86: 312347996 | AQ86: 70.5 | AR86: 227005000 | AS86: 43625666 | AT86: 183379334 | AU86: 80.8 | AV86: 216057000 | AW86: 87088338 | AX86: 128968662 | AY86: 59.7 | AZ86: 0 | BA86: 0 | BB86: 0 | BC86: 0 | BD86: 0 | BE86: 0 | BF86: 0 | BG86: 0 | BH86: 0 | BI86: 0 | BJ86: 0 | BK86: 0 | BL86: 442062000 | BM86: 130714004 | BN86: 311347996 | BO86: 70.4 | BP86: TA Non-Plan Capital
A87: 6* Transport Non Plan C PRJ NL-N-TRN-001 | B87: 1.0133901e+09 | C87: 5.8850746e+08 | D87: 3.2994358e+08 | E87: 9.1845105e+08 | F87: 94939081 | G87: 4.825161e+08 | H87: 4.825161e+08 | I87: 0 | J87: 4.825161e+08 | K87: 0 | L87: 5.3087403e+08 | M87: 1.0599136e+08 | N87: 3.2994358e+08 | O87: 4.3593495e+08 | P87: 94939081 | Q87: 0 | R87: 0 | S87: 0 | T87: 0 | U87: 0 | V87: 0 | W87: 0 | X87: 0 | Y87: 0 | Z87: 0 | AA87: 0 | AB87: 0 | AC87: 0 | AD87: 0 | AE87: 0 | AF87: 1.0133901e+09 | AG87: 5.8850746e+08 | AH87: 3.2994358e+08 | AI87: 9.1845105e+08 | AJ87: 94939081 | AK87: Transport Non Plan C | AL87: NL-N-TRN-001 | AM87: 6* PRJ NL-N-TRN-001 Transport Non Plan C | AN87: 1535600000 | AO87: 588507464 | AP87: 947092536 | AQ87: 61.7 | AR87: 1356600000 | AS87: 482516102 | AT87: 874083898 | AU87: 64.4 | AV87: 179000000 | AW87: 105991362 | AX87: 73008638 | AY87: 40.8 | AZ87: 0 | BA87: 0 | BB87: 0 | BC87: 0 | BD87: 0 | BE87: 0 | BF87: 0 | BG87: 0 | BH87: 0 | BI87: 0 | BJ87: 0 | BK87: 0 | BL87: 1566600000 | BM87: 588507464 | BN87: 978092536 | BO87: 62.4 | BP87: Transport Non Plan C
A88: 6* TPS- I Non Plan CAPE PRJ NL-N-TS1-001 | B88: 14036299 | C88: 10219233 | D88: 215900 | E88: 10435133 | F88: 3601166.1 | G88: 10219233 | H88: 10219233 | I88: 0 | J88: 10219233 | K88: 0 | L88: 3817066.1 | M88: 0 | N88: 215900 | O88: 215900 | P88: 3601166.1 | Q88: 0 | R88: 0 | S88: 0 | T88: 0 | U88: 0 | V88: 0 | W88: 0 | X88: 0 | Y88: 0 | Z88: 0 | AA88: 0 | AB88: 0 | AC88: 0 | AD88: 0 | AE88: 0 | AF88: 14036299 | AG88: 10219233 | AH88: 215900 | AI88: 10435133 | AJ88: 3601166.1 | AK88: TPS- I Non Plan CAPE | AL88: NL-N-TS1-001 | AM88: 6* PRJ NL-N-TS1-001 TPS- I Non Plan CAPE | AN88: 16180000 | AO88: 10219233 | AP88: 5960767 | AQ88: 36.8 | AR88: 16180000 | AS88: 10219233 | AT88: 5960767 | AU88: 36.8 | AV88: 0 | AW88: 0 | AX88: 0 | AY88: 0 | AZ88: 0 | BA88: 0 | BB88: 0 | BC88: 0 | BD88: 0 | BE88: 0 | BF88: 0 | BG88: 0 | BH88: 0 | BI88: 0 | BJ88: 0 | BK88: 0 | BL88: 16180000 | BM88: 10219233 | BN88: 5960767 | BO88: 36.8 | BP88: TPS- I Non Plan CAPE
A89: 6* TPS-II Non Plan CAPE PRJ NL-N-TS2-001 | B89: 25642573 | C89: 14376988 | D89: 5575827.3 | E89: 19952816 | F89: 5689757.8 | G89: 12486301 | H89: 12486301 | I89: 970000 | J89: 13456301 | K89: -970000.01 | L89: 13156272 | M89: 1890686.9 | N89: 4388027.3 | O89: 6278714.2 | P89: 6877557.8 | Q89: 0 | R89: 0 | S89: 217800.02 | T89: 217800.02 | U89: -217800.02 | V89: 0 | W89: 0 | X89: 0 | Y89: 0 | Z89: 0 | AA89: 0 | AB89: 0 | AC89: 0 | AD89: 0 | AE89: 0 | AF89: 25642573 | AG89: 14376988 | AH89: 5575827.3 | AI89: 19952816 | AJ89: 5689757.8 | AK89: TPS-II Non Plan CAPE | AL89: NL-N-TS2-001 | AM89: 6* PRJ NL-N-TS2-001 TPS-II Non Plan CAPE | AN89: 94100006 | AO89: 14376988 | AP89: 79723018 | AQ89: 84.7 | AR89: 94100006 | AS89: 12486301 | AT89: 81613705 | AU89: 86.7 | AV89: 0 | AW89: 1890687 | AX89: -1890687 | AY89: 0 | AZ89: 0 | BA89: 0 | BB89: 0 | BC89: 0 | BD89: 0 | BE89: 0 | BF89: 0 | BG89: 0 | BH89: 0 | BI89: 0 | BJ89: 0 | BK89: 0 | BL89: 94100000 | BM89: 14376988 | BN89: 79723012 | BO89: 84.7 | BP89: TPS-II Non Plan CAPE
A90: 6* TPS-II LEP Stage I & PRJ NL-N-TS2-002 | B90: 6.8694611e+09 | C90: 2.6632298e+09 | D90: 2.5262367e+09 | E90: 5.1894772e+09 | F90: 1.6799839e+09 | G90: 1.9187563e+09 | H90: 1.9162466e+09 | I90: 19297711 | J90: 1.9355551e+09 | K90: -16798747 | L90: 4.9507048e+09 | M90: 7.4698314e+08 | N90: 2.2484655e+09 | O90: 2.9954486e+09 | P90: 1.9552562e+09 | Q90: 0 | R90: 0 | S90: 2.518145e+08 | T90: 2.518145e+08 | U90: -2.518145e+08 | V90: 0 | W90: 0 | X90: 6659010 | Y90: 6659010 | Z90: -6659010 | AA90: 0 | AB90: 0 | AC90: 0 | AD90: 0 | AE90: 0 | AF90: 6.8694611e+09 | AG90: 2.6632298e+09 | AH90: 2.5262367e+09 | AI90: 5.1894772e+09 | AJ90: 1.6799839e+09 | AK90: TPS-II LEP Stage I & | AL90: NL-N-TS2-002 | AM90: 6* PRJ NL-N-TS2-002 TPS-II LEP Stage I & | AN90: 2855912771 | AO90: 2663229780 | AP90: 192682991 | AQ90: 6.7 | AR90: 0 | AS90: 1916246638 | AT90: -1916246638 | AU90: 0 | AV90: 2855912771 | AW90: 746983143 | AX90: 2108929628 | AY90: 73.8 | AZ90: 0 | BA90: 0 | BB90: 0 | BC90: 0 | BD90: 0 | BE90: 0 | BF90: 0 | BG90: 0 | BH90: 0 | BI90: 0 | BJ90: 0 | BK90: 0 | BL90: 2855912771 | BM90: 2663229780 | BN90: 192682991 | BO90: 6.7 | BP90: TPS-II LEP Stage I &
A91: 6* Vigilance Non-Plan C PRJ NL-N-VIG-001 | B91: 9569117.9 | C91: 7388063.8 | D91: 26655.84 | E91: 7414719.7 | F91: 2154398.3 | G91: 7388063.8 | H91: 7388063.8 | I91: 0 | J91: 7388063.8 | K91: 0 | L91: 2181054.1 | M91: 0 | N91: 26655.84 | O91: 26655.84 | P91: 2154398.3 | Q91: 0 | R91: 0 | S91: 0 | T91: 0 | U91: 0 | V91: 0 | W91: 0 | X91: 0 | Y91: 0 | Z91: 0 | AA91: 0 | AB91: 0 | AC91: 0 | AD91: 0 | AE91: 0 | AF91: 9569117.9 | AG91: 7388063.8 | AH91: 26655.84 | AI91: 7414719.7 | AJ91: 2154398.3 | AK91: Vigilance Non-Plan C | AL91: NL-N-VIG-001 | AM91: 6* PRJ NL-N-VIG-001 Vigilance Non-Plan C | AN91: 1174432 | AO91: 7388064 | AP91: -6213632 | AQ91: -529.1 | AR91: 1174432 | AS91: 7388064 | AT91: -6213632 | AU91: -529.1 | AV91: 0 | AW91: 0 | AX91: 0 | AY91: 0 | AZ91: 0 | BA91: 0 | BB91: 0 | BC91: 0 | BD91: 0 | BE91: 0 | BF91: 0 | BG91: 0 | BH91: 0 | BI91: 0 | BJ91: 0 | BK91: 0 | BL91: 1174432 | BM91: 7388064 | BN91: -6213632 | BO91: -529.1 | BP91: Vigilance Non-Plan C
... A95: 6* CSR Administrative O PRJ NL-S-CSR-005 | B95: 20765115 | C95: 20400124 | D95: 365115.43 | E95: 20765240 | F95: -124.16 | G95: 20765115 | H95: 20400124 | I95: 365115.43 | J95: 20765240 | K95: -124.16 | L95: 0 | M95: 0 | N95: 0 | O95: 0 | P95: 0 | Q95: 0 | R95: 0 | S95: 0 | T95: 0 | U95: 0 | V95: 0 | W95: 0 | X95: 0 | Y95: 0 | Z95: 0 | AA95: 0 | AB95: 0 | AC95: 0 | AD95: 0 | AE95: 0 | AF95: 20765115 | AG95: 20400124 | AH95: 365115.43 | AI95: 20765240 | AJ95: -124.16 | AK95: CSR Administrative O | AL95: NL-S-CSR-005 | AM95: 6* PRJ NL-S-CSR-005 CSR Administrative O | AN95: 4500000 | AO95: 20400124 | AP95: -15900124 | AQ95: -353.3 | AR95: 4500000 | AS95: 20400124 | AT95: -15900124 | AU95: -353.3 | AV95: 0 | AW95: 0 | AX95: 0 | AY95: 0 | AZ95: 0 | BA95: 0 | BB95: 0 | BC95: 0 | BD95: 0 | BE95: 0 | BF95: 0 | BG95: 0 | BH95: 0 | BI95: 0 | BJ95: 0 | BK95: 0 | BL95: 4500000 | BM95: 20400124 | BN95: -15900124 | BO95: -353.3 | BP95: CSR Administrative O
A96: 6* CSR Activity 1.2 (15 PRJ NL-S-CSR-006 | B96: 1000000 | C96: 0 | D96: 0 | E96: 0 | F96: 1000000 | G96: 1000000 | H96: 0 | I96: 0 | J96: 0 | K96: 1000000 | L96: 0 | M96: 0 | N96: 0 | O96: 0 | P96: 0 | Q96: 0 | R96: 0 | S96: 0 | T96: 0 | U96: 0 | V96: 0 | W96: 0 | X96: 0 | Y96: 0 | Z96: 0 | AA96: 0 | AB96: 0 | AC96: 0 | AD96: 0 | AE96: 0 | AF96: 2000000 | AG96: 0 | AH96: 0 | AI96: 0 | AJ96: 2000000 | AK96: CSR Activity 1.2 (15 | AL96: NL-S-CSR-006
A97: 6* CSR PBD Proc thro GE PRJ NL-S-CSR-007 | B97: 0 | C97: 0 | D97: 0 | E97: 0 | F97: 0 | G97: 0 | H97: 0 | I97: 0 | J97: 0 | K97: 0 | L97: 0 | M97: 0 | N97: 0 | O97: 0 | P97: 0 | Q97: 0 | R97: 0 | S97: 0 | T97: 0 | U97: 0 | V97: 0 | W97: 0 | X97: 0 | Y97: 0 | Z97: 0 | AA97: 0 | AB97: 0 | AC97: 0 | AD97: 0 | AE97: 0 | AF97: 0 | AG97: 0 | AH97: 0 | AI97: 0 | AJ97: 0 | AK97: CSR PBD Proc thro GE | AL97: NL-S-CSR-007 | AM97: 6* PRJ NL-S-CSR-007 CSR PBD Proc thro GE | AN97: 1040646 | AO97: 0 | AP97: 1040646 | AQ97: 100 | AR97: 1040646 | AS97: 0 | AT97: 1040646 | AU97: 100 | AV97: 0 | AW97: 0 | AX97: 0 | AY97: 0 | AZ97: 0 | BA97: 0 | BB97: 0 | BC97: 0 | BD97: 0 | BE97: 0 | BF97: 0 | BG97: 0 | BH97: 0 | BI97: 0 | BJ97: 0 | BK97: 0 | BL97: 1040646 | BM97: 0 | BN97: 1040646 | BO97: 100 | BP97: CSR PBD Proc thro GE
A98: 6* O2 Plants in Tamilna PRJ NL-S-CSR-008 | B98: 31000000 | C98: 27980751 | D98: 2082090 | E98: 30062840 | F98: 937159.51 | G98: 31000000 | H98: 27980751 | I98: 2082090 | J98: 30062840 | K98: 937159.51 | L98: 0 | M98: 0 | N98: 0 | O98: 0 | P98: 0 | Q98: 0 | R98: 0 | S98: 0 | T98: 0 | U98: 0 | V98: 0 | W98: 0 | X98: 0 | Y98: 0 | Z98: 0 | AA98: 0 | AB98: 0 | AC98: 0 | AD98: 0 | AE98: 0 | AF98: 31000000 | AG98: 27980751 | AH98: 2082090 | AI98: 30062840 | AJ98: 937159.51 | AK98: O2 Plants in Tamilna | AL98: NL-S-CSR-008 | AM98: 6* PRJ NL-S-CSR-008 O2 Plants in Tamilna | AN98: 0 | AO98: 27980751 | AP98: -27980751 | AQ98: 0 | AR98: 0 | AS98: 27980751 | AT98: -27980751 | AU98: 0 | AV98: 0 | AW98: 0 | AX98: 0 | AY98: 0 | AZ98: 0 | BA98: 0 | BB98: 0 | BC98: 0 | BD98: 0 | BE98: 0 | BF98: 0 | BG98: 0 | BH98: 0 | BI98: 0 | BJ98: 0 | BK98: 0 | BL98: 0 | BM98: 27980751 | BN98: -27980751 | BO98: 0 | BP98: O2 Plants in Tamilna
A99: 6* O2 Plants in Karnata PRJ NL-S-CSR-009 | B99: 47320000 | C99: 44806785 | D99: 1577826.8 | E99: 46384612 | F99: 935387.87 | G99: 47320000 | H99: 44806785 | I99: 1577826.8 | J99: 46384612 | K99: 935387.87 | L99: 0 | M99: 0 | N99: 0 | O99: 0 | P99: 0 | Q99: 0 | R99: 0 | S99: 0 | T99: 0 | U99: 0 | V99: 0 | W99: 0 | X99: 0 | Y99: 0 | Z99: 0 | AA99: 0 | AB99: 0 | AC99: 0 | AD99: 0 | AE99: 0 | AF99: 47320000 | AG99: 44806785 | AH99: 1577826.8 | AI99: 46384612 | AJ99: 935387.87 | AK99: O2 Plants in Karnata | AL99: NL-S-CSR-009 | AM99: 6* PRJ NL-S-CSR-009 O2 Plants in Karnata | AN99: 0 | AO99: 44806785 | AP99: -44806785 | AQ99: 0 | AR99: 0 | AS99: 44806785 | AT99: -44806785 | AU99: 0 | AV99: 0 | AW99: 0 | AX99: 0 | AY99: 0 | AZ99: 0 | BA99: 0 | BB99: 0 | BC99: 0 | BD99: 0 | BE99: 0 | BF99: 0 | BG99: 0 | BH99: 0 | BI99: 0 | BJ99: 0 | BK99: 0 | BL99: 0 | BM99: 44806785 | BN99: -44806785 | BO99: 0 | BP99: O2 Plants in Karnata
A100: 6* O2 Plants in Rajasth PRJ NL-S-CSR-010 | B100: 42020000 | C100: 38576718 | D100: 1885287.2 | E100: 40462005 | F100: 1557994.9 | G100: 42020000 | H100: 38576718 | I100: 1885287.2 | J100: 40462005 | K100: 1557994.9 | L100: 0 | M100: 0 | N100: 0 | O100: 0 | P100: 0 | Q100: 0 | R100: 0 | S100: 0 | T100: 0 | U100: 0 | V100: 0 | W100: 0 | X100: 0 | Y100: 0 | Z100: 0 | AA100: 0 | AB100: 0 | AC100: 0 | AD100: 0 | AE100: 0 | AF100: 42020000 | AG100: 38576718 | AH100: 1885287.2 | AI100: 40462005 | AJ100: 1557994.9 | AK100: O2 Plants in Rajasth | AL100: NL-S-CSR-010 | AM100: 6* PRJ NL-S-CSR-010 O2 Plants in Rajasth | AN100: 0 | AO100: 38576718 | AP100: -38576718 | AQ100: 0 | AR100: 0 | AS100: 38576718 | AT100: -38576718 | AU100: 0 | AV100: 0 | AW100: 0 | AX100: 0 | AY100: 0 | AZ100: 0 | BA100: 0 | BB100: 0 | BC100: 0 | BD100: 0 | BE100: 0 | BF100: 0 | BG100: 0 | BH100: 0 | BI100: 0 | BJ100: 0 | BK100: 0 | BL100: 0 | BM100: 38576718 | BN100: -38576718 | BO100: 0 | BP100: O2 Plants in Rajasth
A101: 6* O2 Plants in Odisha PRJ NL-S-CSR-011 | B101: 7120000 | C101: 2256610.2 | D101: 3509135.6 | E101: 5765745.8 | F101: 1354254.2 | G101: 7120000 | H101: 2256610.2 | I101: 3509135.6 | J101: 5765745.8 | K101: 1354254.2 | L101: 0 | M101: 0 | N101: 0 | O101: 0 | P101: 0 | Q101: 0 | R101: 0 | S101: 0 | T101: 0 | U101: 0 | V101: 0 | W101: 0 | X101: 0 | Y101: 0 | Z101: 0 | AA101: 0 | AB101: 0 | AC101: 0 | AD101: 0 | AE101: 0 | AF101: 7120000 | AG101: 2256610.2 | AH101: 3509135.6 | AI101: 5765745.8 | AJ101: 1354254.2 | AK101: O2 Plants in Odisha | AL101: NL-S-CSR-011 | AM101: 6* PRJ NL-S-CSR-011 O2 Plants in Odisha | AN101: 0 | AO101: 2256610 | AP101: -2256610 | AQ101: 0 | AR101: 0 | AS101: 2256610 | AT101: -2256610 | AU101: 0 | AV101: 0 | AW101: 0 | AX101: 0 | AY101: 0 | AZ101: 0 | BA101: 0 | BB101: 0 | BC101: 0 | BD101: 0 | BE101: 0 | BF101: 0 | BG101: 0 | BH101: 0 | BI101: 0 | BJ101: 0 | BK101: 0 | BL101: 0 | BM101: 2256610 | BN101: -2256610 | BO101: 0 | BP101: O2 Plants in Odisha
A102: 6* O2 Concentrators in PRJ NL-S-CSR-012 | B102: 28000000 | C102: 21802057 | D102: 0 | E102: 21802057 | F102: 6197942.8 | G102: 28000000 | H102: 21802057 | I102: 0 | J102: 21802057 | K102: 6197942.8 | L102: 0 | M102: 0 | N102: 0 | O102: 0 | P102: 0 | Q102: 0 | R102: 0 | S102: 0 | T102: 0 | U102: 0 | V102: 0 | W102: 0 | X102: 0 | Y102: 0 | Z102: 0 | AA102: 0 | AB102: 0 | AC102: 0 | AD102: 0 | AE102: 0 | AF102: 28000000 | AG102: 21802057 | AH102: 0 | AI102: 21802057 | AJ102: 6197942.8 | AK102: O2 Concentrators in | AL102: NL-S-CSR-012 | AM102: 6* PRJ NL-S-CSR-012 O2 Concentrators in | AN102: 0 | AO102: 21802057 | AP102: -21802057 | AQ102: 0 | AR102: 0 | AS102: 21802057 | AT102: -21802057 | AU102: 0 | AV102: 0 | AW102: 0 | AX102: 0 | AY102: 0 | AZ102: 0 | BA102: 0 | BB102: 0 | BC102: 0 | BD102: 0 | BE102: 0 | BF102: 0 | BG102: 0 | BH102: 0 | BI102: 0 | BJ102: 0 | BK102: 0 | BL102: 0 | BM102: 21802057 | BN102: -21802057 | BO102: 0 | BP102: O2 Concentrators in
A103: 6* O2 Concentrators in PRJ NL-S-CSR-013 | B103: 14000000 | C103: 10812883 | D103: 0 | E103: 10812883 | F103: 3187117 | G103: 14000000 | H103: 10812883 | I103: 0 | J103: 10812883 | K103: 3187117 | L103: 0 | M103: 0 | N103: 0 | O103: 0 | P103: 0 | Q103: 0 | R103: 0 | S103: 0 | T103: 0 | U103: 0 | V103: 0 | W103: 0 | X103: 0 | Y103: 0 | Z103: 0 | AA103: 0 | AB103: 0 | AC103: 0 | AD103: 0 | AE103: 0 | AF103: 14000000 | AG103: 10812883 | AH103: 0 | AI103: 10812883 | AJ103: 3187117 | AK103: O2 Concentrators in | AL103: NL-S-CSR-013 | AM103: 6* PRJ NL-S-CSR-013 O2 Concentrators in | AN103: 0 | AO103: 10812883 | AP103: -10812883 | AQ103: 0 | AR103: 0 | AS103: 10812883 | AT103: -10812883 | AU103: 0 | AV103: 0 | AW103: 0 | AX103: 0 | AY103: 0 | AZ103: 0 | BA103: 0 | BB103: 0 | BC103: 0 | BD103: 0 | BE103: 0 | BF103: 0 | BG103: 0 | BH103: 0 | BI103: 0 | BJ103: 0 | BK103: 0 | BL103: 0 | BM103: 10812883 | BN103: -10812883 | BO103: 0 | BP103: O2 Concentrators in
A104: 6* O2 Concentrators in PRJ NL-S-CSR-014 | B104: 0 | C104: 0 | D104: 0 | E104: 0 | F104: 0 | G104: 0 | H104: 0 | I104: 0 | J104: 0 | K104: 0 | L104: 0 | M104: 0 | N104: 0 | O104: 0 | P104: 0 | Q104: 0 | R104: 0 | S104: 0 | T104: 0 | U104: 0 | V104: 0 | W104: 0 | X104: 0 | Y104: 0 | Z104: 0 | AA104: 0 | AB104: 0 | AC104: 0 | AD104: 0 | AE104: 0 | AF104: 0 | AG104: 0 | AH104: 0 | AI104: 0 | AJ104: 0 | AK104: O2 Concentrators in | AL104: NL-S-CSR-014
A105: 6* O2 Cylinders & Conce PRJ NL-S-CSR-015 | B105: 0 | C105: 0 | D105: 0 | E105: 0 | F105: 0 | G105: 0 | H105: 0 | I105: 0 | J105: 0 | K105: 0 | L105: 0 | M105: 0 | N105: 0 | O105: 0 | P105: 0 | Q105: 0 | R105: 0 | S105: 0 | T105: 0 | U105: 0 | V105: 0 | W105: 0 | X105: 0 | Y105: 0 | Z105: 0 | AA105: 0 | AB105: 0 | AC105: 0 | AD105: 0 | AE105: 0 | AF105: 0 | AG105: 0 | AH105: 0 | AI105: 0 | AJ105: 0 | AK105: O2 Cylinders & Conce | AL105: NL-S-CSR-015
A106: 6* ICU Beds,Ventillator PRJ NL-S-CSR-016 | B106: 0 | C106: 0 | D106: 0 | E106: 0 | F106: 0 | G106: 0 | H106: 0 | I106: 0 | J106: 0 | K106: 0 | L106: 0 | M106: 0 | N106: 0 | O106: 0 | P106: 0 | Q106: 0 | R106: 0 | S106: 0 | T106: 0 | U106: 0 | V106: 0 | W106: 0 | X106: 0 | Y106: 0 | Z106: 0 | AA106: 0 | AB106: 0 | AC106: 0 | AD106: 0 | AE106: 0 | AF106: 0 | AG106: 0 | AH106: 0 | AI106: 0 | AJ106: 0 | AK106: ICU Beds,Ventillator | AL106: NL-S-CSR-016
A107: 6* Hired BLS Ambulance PRJ NL-S-CSR-017 | B107: 5904000 | C107: 5833542.5 | D107: 0 | E107: 5833542.5 | F107: 70457.51 | G107: 5904000 | H107: 5833542.5 | I107: 0 | J107: 5833542.5 | K107: 70457.51 | L107: 0 | M107: 0 | N107: 0 | O107: 0 | P107: 0 | Q107: 0 | R107: 0 | S107: 0 | T107: 0 | U107: 0 | V107: 0 | W107: 0 | X107: 0 | Y107: 0 | Z107: 0 | AA107: 0 | AB107: 0 | AC107: 0 | AD107: 0 | AE107: 0 | AF107: 5904000 | AG107: 5833542.5 | AH107: 0 | AI107: 5833542.5 | AJ107: 70457.51 | AK107: Hired BLS Ambulance | AL107: NL-S-CSR-017 | AM107: 6* PRJ NL-S-CSR-017 Hired BLS Ambulance | AN107: 0 | AO107: 5833542 | AP107: -5833542 | AQ107: 0 | AR107: 0 | AS107: 5833542 | AT107: -5833542 | AU107: 0 | AV107: 0 | AW107: 0 | AX107: 0 | AY107: 0 | AZ107: 0 | BA107: 0 | BB107: 0 | BC107: 0 | BD107: 0 | BE107: 0 | BF107: 0 | BG107: 0 | BH107: 0 | BI107: 0 | BJ107: 0 | BK107: 0 | BL107: 0 | BM107: 5833542 | BN107: -5833542 | BO107: 0 | BP107: Hired BLS Ambulance
A108: 6* Mask,Sanitizer,Soap PRJ NL-S-CSR-018 | B108: 220000 | C108: 220000 | D108: 0 | E108: 220000 | F108: 0 | G108: 220000 | H108: 220000 | I108: 0 | J108: 220000 | K108: 0 | L108: 0 | M108: 0 | N108: 0 | O108: 0 | P108: 0 | Q108: 0 | R108: 0 | S108: 0 | T108: 0 | U108: 0 | V108: 0 | W108: 0 | X108: 0 | Y108: 0 | Z108: 0 | AA108: 0 | AB108: 0 | AC108: 0 | AD108: 0 | AE108: 0 | AF108: 220000 | AG108: 220000 | AH108: 0 | AI108: 220000 | AJ108: 0 | AK108: Mask,Sanitizer,Soap | AL108: NL-S-CSR-018 | AM108: 6* PRJ NL-S-CSR-018 Mask,Sanitizer,Soap | AN108: 0 | AO108: 220000 | AP108: -220000 | AQ108: 0 | AR108: 0 | AS108: 220000 | AT108: -220000 | AU108: 0 | AV108: 0 | AW108: 0 | AX108: 0 | AY108: 0 | AZ108: 0 | BA108: 0 | BB108: 0 | BC108: 0 | BD108: 0 | BE108: 0 | BF108: 0 | BG108: 0 | BH108: 0 | BI108: 0 | BJ108: 0 | BK108: 0 | BL108: 0 | BM108: 220000 | BN108: -220000 | BO108: 0 | BP108: Mask,Sanitizer,Soap
A109: 6* Sanitizer,Soap Soln PRJ NL-S-CSR-019 | B109: 797000 | C109: 769640.52 | D109: 0 | E109: 769640.52 | F109: 27359.48 | G109: 797000 | H109: 769640.52 | I109: 0 | J109: 769640.52 | K109: 27359.48 | L109: 0 | M109: 0 | N109: 0 | O109: 0 | P109: 0 | Q109: 0 | R109: 0 | S109: 0 | T109: 0 | U109: 0 | V109: 0 | W109: 0 | X109: 0 | Y109: 0 | Z109: 0 | AA109: 0 | AB109: 0 | AC109: 0 | AD109: 0 | AE109: 0 | AF109: 797000 | AG109: 769640.52 | AH109: 0 | AI109: 769640.52 | AJ109: 27359.48 | AK109: Sanitizer,Soap Soln | AL109: NL-S-CSR-019 | AM109: 6* PRJ NL-S-CSR-019 Sanitizer,Soap Soln | AN109: 0 | AO109: 769641 | AP109: -769641 | AQ109: 0 | AR109: 0 | AS109: 769641 | AT109: -769641 | AU109: 0 | AV109: 0 | AW109: 0 | AX109: 0 | AY109: 0 | AZ109: 0 | BA109: 0 | BB109: 0 | BC109: 0 | BD109: 0 | BE109: 0 | BF109: 0 | BG109: 0 | BH109: 0 | BI109: 0 | BJ109: 0 | BK109: 0 | BL109: 0 | BM109: 769641 | BN109: -769641 | BO109: 0 | BP109: Sanitizer,Soap Soln
A110: 6* CC Eqpmt Andaman Nic PRJ NL-S-CSR-020 | B110: 110000 | C110: 109727.77 | D110: 0 | E110: 109727.77 | F110: 272.23 | G110: 110000 | H110: 109727.77 | I110: 0 | J110: 109727.77 | K110: 272.23 | L110: 0 | M110: 0 | N110: 0 | O110: 0 | P110: 0 | Q110: 0 | R110: 0 | S110: 0 | T110: 0 | U110: 0 | V110: 0 | W110: 0 | X110: 0 | Y110: 0 | Z110: 0 | AA110: 0 | AB110: 0 | AC110: 0 | AD110: 0 | AE110: 0 | AF110: 110000 | AG110: 109727.77 | AH110: 0 | AI110: 109727.77 | AJ110: 272.23 | AK110: CC Eqpmt Andaman Nic | AL110: NL-S-CSR-020 | AM110: 6* PRJ NL-S-CSR-020 CC Eqpmt Andaman Nic | AN110: 0 | AO110: 109728 | AP110: -109728 | AQ110: 0 | AR110: 0 | AS110: 109728 | AT110: -109728 | AU110: 0 | AV110: 0 | AW110: 0 | AX110: 0 | AY110: 0 | AZ110: 0 | BA110: 0 | BB110: 0 | BC110: 0 | BD110: 0 | BE110: 0 | BF110: 0 | BG110: 0 | BH110: 0 | BI110: 0 | BJ110: 0 | BK110: 0 | BL110: 0 | BM110: 109728 | BN110: -109728 | BO110: 0 | BP110: CC Eqpmt Andaman Nic
A111: 6* SERI PPE kits to Cud PRJ NL-S-CSR-021 | B111: 3220000 | C111: 3219980 | D111: 0 | E111: 3219980 | F111: 20 | G111: 3220000 | H111: 3219980 | I111: 0 | J111: 3219980 | K111: 20 | L111: 0 | M111: 0 | N111: 0 | O111: 0 | P111: 0 | Q111: 0 | R111: 0 | S111: 0 | T111: 0 | U111: 0 | V111: 0 | W111: 0 | X111: 0 | Y111: 0 | Z111: 0 | AA111: 0 | AB111: 0 | AC111: 0 | AD111: 0 | AE111: 0 | AF111: 3220000 | AG111: 3219980 | AH111: 0 | AI111: 3219980 | AJ111: 20 | AK111: SERI PPE kits to Cud | AL111: NL-S-CSR-021 | AM111: 6* PRJ NL-S-CSR-021 SERI PPE kits to Cud | AN111: 0 | AO111: 3219980 | AP111: -3219980 | AQ111: 0 | AR111: 0 | AS111: 3219980 | AT111: -3219980 | AU111: 0 | AV111: 0 | AW111: 0 | AX111: 0 | AY111: 0 | AZ111: 0 | BA111: 0 | BB111: 0 | BC111: 0 | BD111: 0 | BE111: 0 | BF111: 0 | BG111: 0 | BH111: 0 | BI111: 0 | BJ111: 0 | BK111: 0 | BL111: 0 | BM111: 3219980 | BN111: -3219980 | BO111: 0 | BP111: SERI PPE kits to Cud
A112: 6* Santhigiri Ashram- C PRJ NL-S-CSR-022 | B112: 1000000 | C112: 1000000 | D112: 0 | E112: 1000000 | F112: 0 | G112: 1000000 | H112: 1000000 | I112: 0 | J112: 1000000 | K112: 0 | L112: 0 | M112: 0 | N112: 0 | O112: 0 | P112: 0 | Q112: 0 | R112: 0 | S112: 0 | T112: 0 | U112: 0 | V112: 0 | W112: 0 | X112: 0 | Y112: 0 | Z112: 0 | AA112: 0 | AB112: 0 | AC112: 0 | AD112: 0 | AE112: 0 | AF112: 1000000 | AG112: 1000000 | AH112: 0 | AI112: 1000000 | AJ112: 0 | AK112: Santhigiri Ashram- C | AL112: NL-S-CSR-022 | AM112: 6* PRJ NL-S-CSR-022 Santhigiri Ashram- C | AN112: 0 | AO112: 1000000 | AP112: -1000000 | AQ112: 0 | AR112: 0 | AS112: 1000000 | AT112: -1000000 | AU112: 0 | AV112: 0 | AW112: 0 | AX112: 0 | AY112: 0 | AZ112: 0 | BA112: 0 | BB112: 0 | BC112: 0 | BD112: 0 | BE112: 0 | BF112: 0 | BG112: 0 | BH112: 0 | BI112: 0 | BJ112: 0 | BK112: 0 | BL112: 0 | BM112: 1000000 | BN112: -1000000 | BO112: 0 | BP112: Santhigiri Ashram- C
A113: 6* PPE Kits to GH - Kat PRJ NL-S-CSR-023 | B113: 6000000 | C113: 1385203.5 | D113: 1893527 | E113: 3278730.5 | F113: 2721269.5 | G113: 6000000 | H113: 1385203.5 | I113: 1893527 | J113: 3278730.5 | K113: 2721269.5 | L113: 0 | M113: 0 | N113: 0 | O113: 0 | P113: 0 | Q113: 0 | R113: 0 | S113: 0 | T113: 0 | U113: 0 | V113: 0 | W113: 0 | X113: 0 | Y113: 0 | Z113: 0 | AA113: 0 | AB113: 0 | AC113: 0 | AD113: 0 | AE113: 0 | AF113: 6000000 | AG113: 1385203.5 | AH113: 1893527 | AI113: 3278730.5 | AJ113: 2721269.5 | AK113: PPE Kits to GH - Kat | AL113: NL-S-CSR-023 | AM113: 6* PRJ NL-S-CSR-023 PPE Kits to GH - Kat | AN113: 0 | AO113: 1385203 | AP113: -1385203 | AQ113: 0 | AR113: 0 | AS113: 1385203 | AT113: -1385203 | AU113: 0 | AV113: 0 | AW113: 0 | AX113: 0 | AY113: 0 | AZ113: 0 | BA113: 0 | BB113: 0 | BC113: 0 | BD113: 0 | BE113: 0 | BF113: 0 | BG113: 0 | BH113: 0 | BI113: 0 | BJ113: 0 | BK113: 0 | BL113: 0 | BM113: 1385203 | BN113: -1385203 | BO113: 0 | BP113: PPE Kits to GH - Kat
A114: 6* COVID 19 Measures FD PRJ NL-S-CSR-024 | B114: 20000000 | C114: 11121517 | D114: 0 | E114: 11121517 | F114: 8878483.4 | G114: 20000000 | H114: 11121517 | I114: 0 | J114: 11121517 | K114: 8878483.4 | L114: 0 | M114: 0 | N114: 0 | O114: 0 | P114: 0 | Q114: 0 | R114: 0 | S114: 0 | T114: 0 | U114: 0 | V114: 0 | W114: 0 | X114: 0 | Y114: 0 | Z114: 0 | AA114: 0 | AB114: 0 | AC114: 0 | AD114: 0 | AE114: 0 | AF114: 20000000 | AG114: 11121517 | AH114: 0 | AI114: 11121517 | AJ114: 8878483.4 | AK114: COVID 19 Measures FD | AL114: NL-S-CSR-024 | AM114: 6* PRJ NL-S-CSR-024 COVID 19 Measures FD | AN114: 0 | AO114: 11121517 | AP114: -11121517 | AQ114: 0 | AR114: 0 | AS114: 11121517 | AT114: -11121517 | AU114: 0 | AV114: 0 | AW114: 0 | AX114: 0 | AY114: 0 | AZ114: 0 | BA114: 0 | BB114: 0 | BC114: 0 | BD114: 0 | BE114: 0 | BF114: 0 | BG114: 0 | BH114: 0 | BI114: 0 | BJ114: 0 | BK114: 0 | BL114: 0 | BM114: 11121517 | BN114: -11121517 | BO114: 0 | BP114: COVID 19 Measures FD
A115: 6* Covid Care Hospital PRJ NL-S-CSR-025 | B115: 0 | C115: 0 | D115: 0 | E115: 0 | F115: 0 | G115: 0 | H115: 0 | I115: 0 | J115: 0 | K115: 0 | L115: 0 | M115: 0 | N115: 0 | O115: 0 | P115: 0 | Q115: 0 | R115: 0 | S115: 0 | T115: 0 | U115: 0 | V115: 0 | W115: 0 | X115: 0 | Y115: 0 | Z115: 0 | AA115: 0 | AB115: 0 | AC115: 0 | AD115: 0 | AE115: 0 | AF115: 0 | AG115: 0 | AH115: 0 | AI115: 0 | AJ115: 0 | AK115: Covid Care Hospital | AL115: NL-S-CSR-025
A116: 6* HLL Biotech Ltd PRJ NL-S-CSR-026 | B116: 0 | C116: 0 | D116: 0 | E116: 0 | F116: 0 | G116: 0 | H116: 0 | I116: 0 | J116: 0 | K116: 0 | L116: 0 | M116: 0 | N116: 0 | O116: 0 | P116: 0 | Q116: 0 | R116: 0 | S116: 0 | T116: 0 | U116: 0 | V116: 0 | W116: 0 | X116: 0 | Y116: 0 | Z116: 0 | AA116: 0 | AB116: 0 | AC116: 0 | AD116: 0 | AE116: 0 | AF116: 0 | AG116: 0 | AH116: 0 | AI116: 0 | AJ116: 0 | AK116: HLL Biotech Ltd | AL116: NL-S-CSR-026
A117: 6* Medical Camps PRJ NL-S-CSR-027 | B117: 2500000 | C117: 2425160.3 | D117: 0 | E117: 2425160.3 | F117: 74839.72 | G117: 2500000 | H117: 2425160.3 | I117: 0 | J117: 2425160.3 | K117: 74839.72 | L117: 0 | M117: 0 | N117: 0 | O117: 0 | P117: 0 | Q117: 0 | R117: 0 | S117: 0 | T117: 0 | U117: 0 | V117: 0 | W117: 0 | X117: 0 | Y117: 0 | Z117: 0 | AA117: 0 | AB117: 0 | AC117: 0 | AD117: 0 | AE117: 0 | AF117: 2500000 | AG117: 2425160.3 | AH117: 0 | AI117: 2425160.3 | AJ117: 74839.72 | AK117: Medical Camps | AL117: NL-S-CSR-027 | AM117: 6* PRJ NL-S-CSR-027 Medical Camps | AN117: 0 | AO117: 2425160 | AP117: -2425160 | AQ117: 0 | AR117: 0 | AS117: 2425160 | AT117: -2425160 | AU117: 0 | AV117: 0 | AW117: 0 | AX117: 0 | AY117: 0 | AZ117: 0 | BA117: 0 | BB117: 0 | BC117: 0 | BD117: 0 | BE117: 0 | BF117: 0 | BG117: 0 | BH117: 0 | BI117: 0 | BJ117: 0 | BK117: 0 | BL117: 0 | BM117: 2425160 | BN117: -2425160 | BO117: 0 | BP117: Medical Camps
A118: 6* Swachhta Packwada ac PRJ NL-S-CSR-028 | B118: 1000000 | C118: 942278.86 | D118: 0 | E118: 942278.86 | F118: 57721.14 | G118: 1000000 | H118: 942278.86 | I118: 0 | J118: 942278.86 | K118: 57721.14 | L118: 0 | M118: 0 | N118: 0 | O118: 0 | P118: 0 | Q118: 0 | R118: 0 | S118: 0 | T118: 0 | U118: 0 | V118: 0 | W118: 0 | X118: 0 | Y118: 0 | Z118: 0 | AA118: 0 | AB118: 0 | AC118: 0 | AD118: 0 | AE118: 0 | AF118: 1000000 | AG118: 942278.86 | AH118: 0 | AI118: 942278.86 | AJ118: 57721.14 | AK118: Swachhta Packwada ac | AL118: NL-S-CSR-028 | AM118: 6* PRJ NL-S-CSR-028 Swachhta Packwada ac | AN118: 0 | AO118: 942279 | AP118: -942279 | AQ118: 0 | AR118: 0 | AS118: 942279 | AT118: -942279 | AU118: 0 | AV118: 0 | AW118: 0 | AX118: 0 | AY118: 0 | AZ118: 0 | BA118: 0 | BB118: 0 | BC118: 0 | BD118: 0 | BE118: 0 | BF118: 0 | BG118: 0 | BH118: 0 | BI118: 0 | BJ118: 0 | BK118: 0 | BL118: 0 | BM118: 942279 | BN118: -942279 | BO118: 0 | BP118: Swachhta Packwada ac
A119: 6* Nutritional Support PRJ NL-S-CSR-029 | B119: 4000000 | C119: 2519727.8 | D119: 1173152.7 | E119: 3692880.5 | F119: 307119.5 | G119: 4000000 | H119: 2519727.8 | I119: 1173152.7 | J119: 3692880.5 | K119: 307119.5 | L119: 0 | M119: 0 | N119: 0 | O119: 0 | P119: 0 | Q119: 0 | R119: 0 | S119: 0 | T119: 0 | U119: 0 | V119: 0 | W119: 0 | X119: 0 | Y119: 0 | Z119: 0 | AA119: 0 | AB119: 0 | AC119: 0 | AD119: 0 | AE119: 0 | AF119: 4000000 | AG119: 2519727.8 | AH119: 1173152.7 | AI119: 3692880.5 | AJ119: 307119.5 | AK119: Nutritional Support | AL119: NL-S-CSR-029 | AM119: 6* PRJ NL-S-CSR-029 Nutritional Support | AN119: 0 | AO119: 2519728 | AP119: -2519728 | AQ119: 0 | AR119: 0 | AS119: 2519728 | AT119: -2519728 | AU119: 0 | AV119: 0 | AW119: 0 | AX119: 0 | AY119: 0 | AZ119: 0 | BA119: 0 | BB119: 0 | BC119: 0 | BD119: 0 | BE119: 0 | BF119: 0 | BG119: 0 | BH119: 0 | BI119: 0 | BJ119: 0 | BK119: 0 | BL119: 0 | BM119: 2519728 | BN119: -2519728 | BO119: 0 | BP119: Nutritional Support
...

Sheet Analysis
A1: Project ID | B1: NL-N-TS2-001 | C1: =MATCH(B1,Budget!AL3:AL411,0) -> 86 | D1: {=INDEX(Budget!$A$3:$AJ$411,$C$1,1)} -> 6* TPS-II Non Plan CAPE PRJ NL-N-TS2-001 | E1: {=INDEX(Budget!$B$3:$AJ$411,$C$1,$C$2)} -> 25642573 | F1: {=INDEX(Budget!$B$3:$AJ$411,$C$1,$C$2)} -> 25642573 | G1: {=INDEX(Budget!$B$3:$AJ$411,$C$1,$C$2)} -> 25642573 | H1: {=INDEX(Budget!$B$3:$AJ$411,$C$1,$C$2)} -> 25642573
A2: Years | B2: Total of years | C2: =MATCH($B$2,Budget!$B$1:$AF$1,0) -> 1
C3: Plan | D3: Budget | E3: Actual | F3: Commitment | G3: Assigned | H3: Available
C4: {=INDEX(Budget!$AM$3:$AS$411,$C$1,INT($C$2/5)+1)} -> 94100006 | D4: {=INDEX(Budget!$B$3:$AJ$411,$C$1,$C$2)} -> 25642573 | E4: {=INDEX(Budget!$B$3:$AJ$411,$C$1,$C$2+1)} -> 14376988 | F4: {=INDEX(Budget!$B$3:$AJ$411,$C$1,$C$2+2)} -> 5575827.3 | G4: {=INDEX(Budget!$B$3:$AJ$411,$C$1,$C$2+3)} -> 19952816 | H4: {=INDEX(Budget!$B$3:$AJ$411,$C$1,$C$2+4)} -> 5689757.8
